{"resource": "boxscore", "resultSets": [{"headers": ["GAME_DATE_EST", "GAME_SEQUENCE", "GAME_ID", "GAME_STATUS_ID", "GAME_STATUS_TEXT", "GAMECODE", "HOME_TEAM_ID", "VISITOR_TEAM_ID", "SEASON", "LIVE_PERIOD", "LIVE_PC_TIME", "NATL_TV_BROADCASTER_ABBREVIATION", "LIVE_PERIOD_TIME_BCAST", "WH_STATUS"], "rowSet": [["2011-03-20T00:00:00", 6, "0021001040", 3, "Final", "20110320/UTAHOU", 1610612745, 1610612762, "2010", 4, "", null, "Q4  - ", 1]], "name": "GameSummary"}, {"headers": ["GAME_DATE_EST", "GAME_SEQUENCE", "GAME_ID", "TEAM_ID", "TEAM_ABBREVIATION", "TEAM_CITY_NAME", "TEAM_WINS_LOSSES", "PTS_QTR1", "PTS_QTR2", "PTS_QTR3", "PTS_QTR4", "PTS_OT1", "PTS_OT2", "PTS_OT3", "PTS_OT4", "PTS_OT5", "PTS_OT6", "PTS_OT7", "PTS_OT8", "PTS_OT9", "PTS_OT10", "PTS"], "rowSet": [["2011-03-20T00:00:00", 6, "0021001040", 1610612762, "UTA", "Utah", "36-34", 19, 28, 28, 33, 0, 0, 0, 0, 0, 0, 0, 0, 0, 0, 108], ["2011-03-20T00:00:00", 6, "0021001040", 1610612745, "HOU", "Houston", "37-34", 30, 25, 22, 33, 0, 0, 0, 0, 0, 0, 0, 0, 0, 0, 110]], "name": "LineScore"}, {"headers": ["GAME_ID", "HOME_TEAM_ID", "VISITOR_TEAM_ID", "GAME_DATE_EST", "HOME_TEAM_WINS", "HOME_TEAM_LOSSES", "SERIES_LEADER"], "rowSet": [["0021001040", 1610612745, 1610612762, "2011-03-20T00:00:00", 2, 1, "Houston"]], "name": "SeasonSeries"}, {"headers": ["GAME_ID", "LAST_GAME_ID", "LAST_GAME_DATE_EST", "LAST_GAME_HOME_TEAM_ID", "LAST_GAME_HOME_TEAM_CITY", "LAST_GAME_HOME_TEAM_NAME", "LAST_GAME_HOME_TEAM_ABBREVIATION", "LAST_GAME_HOME_TEAM_POINTS", "LAST_GAME_VISITOR_TEAM_ID", "LAST_GAME_VISITOR_TEAM_CITY", "LAST_GAME_VISITOR_TEAM_NAME", "LAST_GAME_VISITOR_TEAM_CITY1", "LAST_GAME_VISITOR_TEAM_POINTS"], "rowSet": [["0021001040", "0021000728", "2011-02-02T00:00:00", 1610612745, "Houston", "Rockets", "HOU", 97, 1610612762, "Utah", "Jazz", "UTA", 96]], "name": "LastMeeting"}, {"headers": ["GAME_ID", "TEAM_ID", "TEAM_ABBREVIATION", "TEAM_CITY", "PLAYER_ID", "PLAYER_NAME", "START_POSITION", "COMMENT", "MIN", "FGM", "FGA", "FG_PCT", "FG3M", "FG3A", "FG3_PCT", "FTM", "FTA", "FT_PCT", "OREB", "DREB", "REB", "AST", "STL", "BLK", "TO", "PF", "PTS", "PLUS_MINUS"], "rowSet": [["0021001040", 1610612762, "UTA", "Utah", 1905, "Andrei Kirilenko", "F", "", "20:37", 4, 7, 0.571, 1, 1, 1.0, 1, 2, 0.5, 4, 0, 4, 3, 1, 1, 1, 1, 10, 5.0], ["0021001040", 1610612762, "UTA", "Utah", 200794, "Paul Millsap", "F", "", "38:57", 12, 18, 0.667, 2, 3, 0.667, 9, 12, 0.75, 3, 7, 10, 4, 1, 3, 1, 5, 35, 9.0], ["0021001040", 1610612762, "UTA", "Utah", 2744, "Al Jefferson", "C", "", "37:53", 7, 23, 0.304, 0, 0, 0.0, 3, 5, 0.6, 9, 10, 19, 4, 0, 1, 2, 3, 17, -5.0], ["0021001040", 1610612762, "UTA", "Utah", 101139, "CJ Miles", "G", "", "33:09", 8, 16, 0.5, 2, 5, 0.4, 1, 2, 0.5, 1, 1, 2, 2, 0, 0, 1, 3, 19, -2.0], ["0021001040", 1610612762, "UTA", "Utah", 2734, "Devin Harris", "G", "", "29:55", 4, 15, 0.267, 2, 4, 0.5, 2, 4, 0.5, 0, 5, 5, 3, 0, 0, 4, 4, 12, 1.0], ["0021001040", 1610612762, "UTA", "Utah", 1952, "Raja Bell", "", "", "29:10", 1, 4, 0.25, 0, 1, 0.0, 0, 0, 0.0, 1, 4, 5, 1, 0, 0, 2, 5, 2, -5.0], ["0021001040", 1610612762, "UTA", "Utah", 202324, "Derrick Favors", "", "", "19:02", 4, 9, 0.444, 0, 0, 0.0, 0, 0, 0.0, 2, 2, 4, 0, 0, 1, 1, 1, 8, -7.0], ["0021001040", 1610612762, "UTA", "Utah", 2248, "Earl Watson", "", "", "18:05", 0, 2, 0.0, 0, 1, 0.0, 0, 0, 0.0, 0, 1, 1, 2, 0, 0, 1, 2, 0, -3.0], ["0021001040", 1610612762, "UTA", "Utah", 202330, "Gordon Hayward", "", "", "13:12", 2, 3, 0.667, 1, 1, 1.0, 0, 0, 0.0, 2, 0, 2, 1, 0, 0, 1, 2, 5, -3.0], ["0021001040", 1610612762, "UTA", "Utah", 202379, "Jeremy Evans", "", "DNP - Coach's Decision", null, null, null, null, null, null, null, null, null, null, null, null, null, null, null, null, null, null, null, null], ["0021001040", 1610612762, "UTA", "Utah", 201178, "Kyrylo Fesenko", "", "DNP - Coach's Decision", null, null, null, null, null, null, null, null, null, null, null, null, null, null, null, null, null, null, null, null], ["0021001040", 1610612762, "UTA", "Utah", 101179, "Ronnie Price", "", "DNP - Coach's Decision", null, null, null, null, null, null, null, null, null, null, null, null, null, null, null, null, null, null, null, null], ["0021001040", 1610612745, "HOU", "Houston", 201978, "Chase Budinger", "F", "", "9:18", 2, 4, 0.5, 1, 1, 1.0, 2, 2, 1.0, 0, 1, 1, 0, 0, 0, 2, 1, 7, 1.0], ["0021001040", 1610612745, "HOU", "Houston", 2449, "Luis Scola", "F", "", "20:22", 1, 5, 0.2, 0, 0, 0.0, 2, 3, 0.667, 2, 6, 8, 0, 1, 3, 2, 4, 4, -5.0], ["0021001040", 1610612745, "HOU", "Houston", 101236, "Charles Hayes", "C", "", "35:57", 3, 11, 0.273, 0, 0, 0.0, 1, 2, 0.5, 2, 3, 5, 4, 0, 2, 1, 3, 7, 3.0], ["0021001040", 1610612745, "HOU", "Houston", 2755, "Kevin Martin", "G", "", "41:43", 7, 18, 0.389, 2, 8, 0.25, 18, 18, 1.0, 0, 3, 3, 1, 1, 0, 2, 0, 34, 6.0], ["0021001040", 1610612745, "HOU", "Houston", 200768, "Kyle Lowry", "G", "", "43:39", 9, 14, 0.643, 3, 4, 0.75, 7, 8, 0.875, 3, 8, 11, 10, 3, 0, 1, 3, 28, 0.0], ["0021001040", 1610612745, "HOU", "Houston", 201584, "Courtney Lee", "", "", "40:08", 2, 9, 0.222, 0, 3, 0.0, 4, 6, 0.667, 1, 2, 3, 2, 1, 0, 0, 0, 8, 0.0], ["0021001040", 1610612745, "HOU", "Houston", 202335, "Patrick Patterson", "", "", "27:38", 7, 11, 0.636, 0, 0, 0.0, 0, 0, 0.0, 4, 9, 13, 0, 0, 1, 2, 4, 14, 7.0], ["0021001040", 1610612745, "HOU", "Houston", 201941, "Jordan Hill", "", "", "12:03", 0, 5, 0.0, 0, 0, 0.0, 2, 2, 1.0, 2, 2, 4, 0, 0, 0, 0, 3, 2, -1.0], ["0021001040", 1610612745, "HOU", "Houston", 201609, "Goran Dragic", "", "", "9:12", 2, 5, 0.4, 2, 3, 0.667, 0, 0, 0.0, 0, 0, 0, 1, 0, 0, 0, 2, 6, -1.0], ["0021001040", 1610612745, "HOU", "Houston", 201960, "DeMarre Carroll", "", "DNP - Coach's Decision", null, null, null, null, null, null, null, null, null, null, null, null, null, null, null, null, null, null, null, null], ["0021001040", 1610612745, "HOU", "Houston", 1802, "Brad Miller", "", "DNP - Coach's Decision", null, null, null, null, null, null, null, null, null, null, null, null, null, null, null, null, null, null, null, null], ["0021001040", 1610612745, "HOU", "Houston", 201944, "Terrence Williams", "", "DNP - Coach's Decision", null, null, null, null, null, null, null, null, null, null, null, null, null, null, null, null, null, null, null, null]], "name": "PlayerStats"}, {"headers": ["GAME_ID", "TEAM_ID", "TEAM_NAME", "TEAM_ABBREVIATION", "TEAM_CITY", "MIN", "FGM", "FGA", "FG_PCT", "FG3M", "FG3A", "FG3_PCT", "FTM", "FTA", "FT_PCT", "OREB", "DREB", "REB", "AST", "STL", "BLK", "TO", "PF", "PTS", "PLUS_MINUS"], "rowSet": [["0021001040", 1610612762, "Jazz", "UTA", "Utah", "240:00", 42, 97, 0.433, 8, 16, 0.5, 16, 25, 0.64, 22, 30, 52, 20, 2, 6, 14, 26, 108, -2.0], ["0021001040", 1610612745, "Rockets", "HOU", "Houston", "240:00", 33, 82, 0.402, 8, 19, 0.421, 36, 41, 0.878, 14, 34, 48, 18, 6, 6, 10, 20, 110, 2.0]], "name": "TeamStats"}, {"headers": ["LEAGUE_ID", "SEASON_ID", "TEAM_ID", "TEAM_ABBREVIATION", "TEAM_CITY", "PTS_PAINT", "PTS_2ND_CHANCE", "PTS_FB", "LARGEST_LEAD", "LEAD_CHANGES", "TIMES_TIED"], "rowSet": [["00", "22010", 1610612745, "HOU", "Houston", 36, 22, 14, 12, 2, 4], ["00", "22010", 1610612762, "UTA", "Utah", 48, 34, 14, 12, 2, 4]], "name": "OtherStats"}, {"headers": ["OFFICIAL_ID", "FIRST_NAME", "LAST_NAME", "JERSEY_NUM"], "rowSet": [[1188, "Leroy", "Richardson", "20"], [2148, "Mark", "Ayotte", "56"], [1662, "Bill", "Kennedy", "55"]], "name": "Officials"}, {"headers": ["GAME_DATE", "ATTENDANCE", "GAME_TIME"], "rowSet": [["SUNDAY, MARCH 20, 2011", 14459, "2:16"]], "name": "GameInfo"}, {"headers": ["PLAYER_ID", "FIRST_NAME", "LAST_NAME", "JERSEY_NUM", "TEAM_ID", "TEAM_CITY", "TEAM_NAME", "TEAM_ABBREVIATION"], "rowSet": [[2246, "Mehmet", "Okur", "13", 1610612762, "Utah", "Jazz", "UTA"], [1922, "Francisco", "Elson", "16", 1610612762, "Utah", "Jazz", "UTA"], [2397, "Ming", "Yao", "11", 1610612745, "Houston", "Rockets", "HOU"], [201934, "Hasheem", "Thabeet", "32", 1610612745, "Houston", "Rockets", "HOU"]], "name": "InactivePlayers"}, {"headers": ["VIDEO_AVAILABLE_FLAG"], "rowSet": [[0]], "name": "AvailableVideo"}], "parameters": {"GameID": "0021001040", "RangeType": 0, "StartPeriod": 0, "StartRange": 0, "EndPeriod": 0, "EndRange": 0}}