{"resource": "boxscore", "resultSets": [{"headers": ["GAME_DATE_EST", "GAME_SEQUENCE", "GAME_ID", "GAME_STATUS_ID", "GAME_STATUS_TEXT", "GAMECODE", "HOME_TEAM_ID", "VISITOR_TEAM_ID", "SEASON", "LIVE_PERIOD", "LIVE_PC_TIME", "NATL_TV_BROADCASTER_ABBREVIATION", "LIVE_PERIOD_TIME_BCAST", "WH_STATUS"], "rowSet": [["2013-02-01T00:00:00", 3, "0021200686", 3, "Final", "20130201/ORLBOS", 1610612738, 1610612753, "2012", 4, "", null, "Q4  - ", 1]], "name": "GameSummary"}, {"headers": ["GAME_DATE_EST", "GAME_SEQUENCE", "GAME_ID", "TEAM_ID", "TEAM_ABBREVIATION", "TEAM_CITY_NAME", "TEAM_WINS_LOSSES", "PTS_QTR1", "PTS_QTR2", "PTS_QTR3", "PTS_QTR4", "PTS_OT1", "PTS_OT2", "PTS_OT3", "PTS_OT4", "PTS_OT5", "PTS_OT6", "PTS_OT7", "PTS_OT8", "PTS_OT9", "PTS_OT10", "PTS"], "rowSet": [["2013-02-01T00:00:00", 3, "0021200686", 1610612753, "ORL", "Orlando", "14-32", 18, 17, 24, 25, 0, 0, 0, 0, 0, 0, 0, 0, 0, 0, 84], ["2013-02-01T00:00:00", 3, "0021200686", 1610612738, "BOS", "Boston", "23-23", 25, 21, 26, 25, 0, 0, 0, 0, 0, 0, 0, 0, 0, 0, 97]], "name": "LineScore"}, {"headers": ["GAME_ID", "HOME_TEAM_ID", "VISITOR_TEAM_ID", "GAME_DATE_EST", "HOME_TEAM_WINS", "HOME_TEAM_LOSSES", "SERIES_LEADER"], "rowSet": [["0021200686", 1610612738, 1610612753, "2013-02-01T00:00:00", 3, 0, "Boston"]], "name": "SeasonSeries"}, {"headers": ["GAME_ID", "LAST_GAME_ID", "LAST_GAME_DATE_EST", "LAST_GAME_HOME_TEAM_ID", "LAST_GAME_HOME_TEAM_CITY", "LAST_GAME_HOME_TEAM_NAME", "LAST_GAME_HOME_TEAM_ABBREVIATION", "LAST_GAME_HOME_TEAM_POINTS", "LAST_GAME_VISITOR_TEAM_ID", "LAST_GAME_VISITOR_TEAM_CITY", "LAST_GAME_VISITOR_TEAM_NAME", "LAST_GAME_VISITOR_TEAM_CITY1", "LAST_GAME_VISITOR_TEAM_POINTS"], "rowSet": [["0021200686", "0021200195", "2012-11-25T00:00:00", 1610612738, "Boston", "Celtics", "BOS", 116, 1610612753, "Orlando", "Magic", "ORL", 110]], "name": "LastMeeting"}, {"headers": ["GAME_ID", "TEAM_ID", "TEAM_ABBREVIATION", "TEAM_CITY", "PLAYER_ID", "PLAYER_NAME", "START_POSITION", "COMMENT", "MIN", "FGM", "FGA", "FG_PCT", "FG3M", "FG3A", "FG3_PCT", "FTM", "FTA", "FT_PCT", "OREB", "DREB", "REB", "AST", "STL", "BLK", "TO", "PF", "PTS", "PLUS_MINUS"], "rowSet": [["0021200686", 1610612753, "ORL", "Orlando", 203090, "Maurice Harkless", "F", "", "30:17", 4, 10, 0.4, 0, 2, 0.0, 0, 0, 0.0, 4, 4, 8, 2, 2, 0, 0, 2, 8, -2.0], ["0021200686", 1610612753, "ORL", "Orlando", 203094, "Andrew Nicholson", "F", "", "32:50", 6, 13, 0.462, 0, 0, 0.0, 2, 2, 1.0, 0, 10, 10, 1, 1, 2, 3, 0, 14, 7.0], ["0021200686", 1610612753, "ORL", "Orlando", 202696, "Nikola Vucevic", "C", "", "32:15", 6, 12, 0.5, 0, 0, 0.0, 2, 2, 1.0, 5, 9, 14, 1, 0, 2, 1, 4, 14, -10.0], ["0021200686", 1610612753, "ORL", "Orlando", 200755, "JJ Redick", "G", "", "32:59", 5, 15, 0.333, 2, 5, 0.4, 3, 3, 1.0, 0, 2, 2, 5, 2, 0, 3, 0, 15, -7.0], ["0021200686", 1610612753, "ORL", "Orlando", 2749, "Jameer Nelson", "G", "", "18:30", 1, 6, 0.167, 0, 3, 0.0, 0, 0, 0.0, 0, 0, 0, 2, 1, 0, 2, 1, 2, -5.0], ["0021200686", 1610612753, "ORL", "Orlando", 203199, "DeQuan Jones", "", "", "13:45", 0, 4, 0.0, 0, 1, 0.0, 0, 0, 0.0, 0, 1, 1, 0, 0, 1, 0, 0, 0, -21.0], ["0021200686", 1610612753, "ORL", "Orlando", 201177, "Josh McRoberts", "", "", "7:46", 0, 2, 0.0, 0, 1, 0.0, 0, 0, 0.0, 0, 2, 2, 0, 0, 0, 0, 1, 0, -12.0], ["0021200686", 1610612753, "ORL", "Orlando", 202734, "E'Twaun Moore", "", "", "24:21", 6, 14, 0.429, 1, 3, 0.333, 1, 1, 1.0, 1, 3, 4, 4, 1, 0, 3, 1, 14, 0.0], ["0021200686", 1610612753, "ORL", "Orlando", 202397, "Ish Smith", "", "", "15:16", 3, 6, 0.5, 0, 0, 0.0, 0, 0, 0.0, 1, 0, 1, 1, 2, 0, 1, 0, 6, -1.0], ["0021200686", 1610612753, "ORL", "Orlando", 2045, "Hedo Turkoglu", "", "", "17:50", 0, 6, 0.0, 0, 4, 0.0, 0, 0, 0.0, 0, 0, 0, 1, 1, 0, 0, 1, 0, -19.0], ["0021200686", 1610612753, "ORL", "Orlando", 202970, "Gustavo Ayon", "", "", "7:07", 0, 1, 0.0, 0, 0, 0.0, 0, 0, 0.0, 1, 1, 2, 1, 0, 1, 1, 2, 0, -5.0], ["0021200686", 1610612753, "ORL", "Orlando", 203124, "Kyle O'Quinn", "", "", "7:05", 5, 6, 0.833, 0, 0, 0.0, 1, 1, 1.0, 3, 0, 3, 1, 0, 0, 0, 1, 11, 10.0], ["0021200686", 1610612753, "ORL", "Orlando", 201175, "Glen Davis", "", "NWT - Fractured Left Foot", null, null, null, null, null, null, null, null, null, null, null, null, null, null, null, null, null, null, null, null], ["0021200686", 1610612738, "BOS", "Boston", 1718, "Paul Pierce", "F", "", "28:46", 5, 10, 0.5, 1, 4, 0.25, 3, 6, 0.5, 0, 11, 11, 7, 1, 0, 3, 2, 14, 10.0], ["0021200686", 1610612738, "BOS", "Boston", 101138, "Brandon Bass", "F", "", "26:27", 2, 6, 0.333, 0, 0, 0.0, 2, 2, 1.0, 2, 5, 7, 1, 0, 0, 1, 1, 6, -15.0], ["0021200686", 1610612738, "BOS", "Boston", 708, "Kevin Garnett", "C", "", "22:42", 7, 12, 0.583, 0, 0, 0.0, 0, 0, 0.0, 4, 6, 10, 1, 3, 1, 0, 0, 14, 9.0], ["0021200686", 1610612738, "BOS", "Boston", 202340, "Avery Bradley", "G", "", "20:19", 3, 9, 0.333, 0, 2, 0.0, 0, 0, 0.0, 0, 2, 2, 2, 0, 0, 2, 3, 6, -10.0], ["0021200686", 1610612738, "BOS", "Boston", 201584, "Courtney Lee", "G", "", "38:58", 6, 13, 0.462, 2, 4, 0.5, 0, 0, 0.0, 1, 4, 5, 5, 2, 0, 2, 0, 14, -5.0], ["0021200686", 1610612738, "BOS", "Boston", 2215, "Jason Collins", "", "", "11:09", 0, 0, 0.0, 0, 0, 0.0, 0, 0, 0.0, 2, 1, 3, 0, 0, 0, 2, 1, 0, 11.0], ["0021200686", 1610612738, "BOS", "Boston", 1891, "Jason Terry", "", "", "27:51", 4, 8, 0.5, 1, 4, 0.25, 3, 3, 1.0, 0, 1, 1, 5, 0, 0, 1, 3, 12, 23.0], ["0021200686", 1610612738, "BOS", "Boston", 201145, "Jeff Green", "", "", "29:07", 8, 14, 0.571, 0, 1, 0.0, 1, 3, 0.333, 1, 3, 4, 4, 1, 3, 3, 2, 17, 20.0], ["0021200686", 1610612738, "BOS", "Boston", 2571, "Leandro Barbosa", "", "", "26:46", 6, 11, 0.545, 0, 3, 0.0, 0, 0, 0.0, 0, 2, 2, 4, 0, 0, 0, 0, 12, 21.0], ["0021200686", 1610612738, "BOS", "Boston", 2404, "Chris Wilcox", "", "", "5:17", 1, 1, 1.0, 0, 0, 0.0, 0, 0, 0.0, 0, 3, 3, 1, 1, 1, 0, 1, 2, 2.0], ["0021200686", 1610612738, "BOS", "Boston", 203097, "Fab Melo", "", "", "2:38", 0, 0, 0.0, 0, 0, 0.0, 0, 0, 0.0, 0, 0, 0, 0, 1, 0, 0, 0, 0, -1.0], ["0021200686", 1610612738, "BOS", "Boston", 200765, "Rajon Rondo", "", "NWT - Torn ACL, Right Knee", null, null, null, null, null, null, null, null, null, null, null, null, null, null, null, null, null, null, null, null]], "name": "PlayerStats"}, {"headers": ["GAME_ID", "TEAM_ID", "TEAM_NAME", "TEAM_ABBREVIATION", "TEAM_CITY", "MIN", "FGM", "FGA", "FG_PCT", "FG3M", "FG3A", "FG3_PCT", "FTM", "FTA", "FT_PCT", "OREB", "DREB", "REB", "AST", "STL", "BLK", "TO", "PF", "PTS", "PLUS_MINUS"], "rowSet": [["0021200686", 1610612753, "Magic", "ORL", "Orlando", "240:00", 36, 95, 0.379, 3, 19, 0.158, 9, 9, 1.0, 15, 32, 47, 19, 10, 6, 14, 13, 84, -13.0], ["0021200686", 1610612738, "Celtics", "BOS", "Boston", "240:00", 42, 84, 0.5, 4, 18, 0.222, 9, 14, 0.643, 10, 38, 48, 30, 9, 5, 14, 13, 97, 13.0]], "name": "TeamStats"}, {"headers": ["LEAGUE_ID", "SEASON_ID", "TEAM_ID", "TEAM_ABBREVIATION", "TEAM_CITY", "PTS_PAINT", "PTS_2ND_CHANCE", "PTS_FB", "LARGEST_LEAD", "LEAD_CHANGES", "TIMES_TIED"], "rowSet": [["00", "22012", 1610612738, "BOS", "Boston", 56, 10, 10, 23, 5, 4], ["00", "22012", 1610612753, "ORL", "Orlando", 52, 17, 15, 23, 5, 4]], "name": "OtherStats"}, {"headers": ["OFFICIAL_ID", "FIRST_NAME", "LAST_NAME", "JERSEY_NUM"], "rowSet": [[1195, "Derrick", "Stafford", "9"], [201637, "Haywoode", "Workman", "66"], [202027, "Tre", "Maddox", "73"]], "name": "Officials"}, {"headers": ["GAME_DATE", "ATTENDANCE", "GAME_TIME"], "rowSet": [["FRIDAY, FEBRUARY 1, 2013", 18624, "2:02"]], "name": "GameInfo"}, {"headers": ["PLAYER_ID", "FIRST_NAME", "LAST_NAME", "JERSEY_NUM", "TEAM_ID", "TEAM_CITY", "TEAM_NAME", "TEAM_ABBREVIATION"], "rowSet": [[203096, "Jared", "Sullinger", " 7", 1610612738, "Boston", "Celtics", "BOS"], [1733, "Al", "Harrington", " 3", 1610612753, "Orlando", "Magic", "ORL"], [201167, "Arron", "Afflalo", " 4", 1610612753, "Orlando", "Magic", "ORL"]], "name": "InactivePlayers"}, {"headers": ["VIDEO_AVAILABLE_FLAG"], "rowSet": [[1]], "name": "AvailableVideo"}], "parameters": {"GameID": "0021200686", "RangeType": 0, "StartPeriod": 0, "StartRange": 0, "EndPeriod": 0, "EndRange": 0}}