{"resource": "boxscore", "resultSets": [{"headers": ["GAME_DATE_EST", "GAME_SEQUENCE", "GAME_ID", "GAME_STATUS_ID", "GAME_STATUS_TEXT", "GAMECODE", "HOME_TEAM_ID", "VISITOR_TEAM_ID", "SEASON", "LIVE_PERIOD", "LIVE_PC_TIME", "NATL_TV_BROADCASTER_ABBREVIATION", "LIVE_PERIOD_TIME_BCAST", "WH_STATUS"], "rowSet": [["2014-01-20T00:00:00", 10, "0021300615", 3, "Final", "20140120/INDGSW", 1610612744, 1610612754, "2013", 4, "", "TNT", "Q4  - TNT", 1]], "name": "GameSummary"}, {"headers": ["GAME_DATE_EST", "GAME_SEQUENCE", "GAME_ID", "TEAM_ID", "TEAM_ABBREVIATION", "TEAM_CITY_NAME", "TEAM_WINS_LOSSES", "PTS_QTR1", "PTS_QTR2", "PTS_QTR3", "PTS_QTR4", "PTS_OT1", "PTS_OT2", "PTS_OT3", "PTS_OT4", "PTS_OT5", "PTS_OT6", "PTS_OT7", "PTS_OT8", "PTS_OT9", "PTS_OT10", "PTS"], "rowSet": [["2014-01-20T00:00:00", 10, "0021300615", 1610612744, "GSW", "Golden State", "26-17", 21, 19, 29, 25, 0, 0, 0, 0, 0, 0, 0, 0, 0, 0, 94], ["2014-01-20T00:00:00", 10, "0021300615", 1610612754, "IND", "Indiana", "33-7", 35, 18, 24, 25, 0, 0, 0, 0, 0, 0, 0, 0, 0, 0, 102]], "name": "LineScore"}, {"headers": ["GAME_ID", "HOME_TEAM_ID", "VISITOR_TEAM_ID", "GAME_DATE_EST", "HOME_TEAM_WINS", "HOME_TEAM_LOSSES", "SERIES_LEADER"], "rowSet": [["0021300615", 1610612744, 1610612754, "2014-01-20T00:00:00", 0, 1, "Indiana"]], "name": "SeasonSeries"}, {"headers": ["GAME_ID", "LAST_GAME_ID", "LAST_GAME_DATE_EST", "LAST_GAME_HOME_TEAM_ID", "LAST_GAME_HOME_TEAM_CITY", "LAST_GAME_HOME_TEAM_NAME", "LAST_GAME_HOME_TEAM_ABBREVIATION", "LAST_GAME_HOME_TEAM_POINTS", "LAST_GAME_VISITOR_TEAM_ID", "LAST_GAME_VISITOR_TEAM_CITY", "LAST_GAME_VISITOR_TEAM_NAME", "LAST_GAME_VISITOR_TEAM_CITY1", "LAST_GAME_VISITOR_TEAM_POINTS"], "rowSet": [["0021300615", "0021200844", "2013-02-26T00:00:00", 1610612744, "Golden State", "Warriors", "GSW", 97, 1610612754, "Indiana", "Pacers", "IND", 108]], "name": "LastMeeting"}, {"headers": ["GAME_ID", "TEAM_ID", "TEAM_ABBREVIATION", "TEAM_CITY", "PLAYER_ID", "PLAYER_NAME", "START_POSITION", "COMMENT", "MIN", "FGM", "FGA", "FG_PCT", "FG3M", "FG3A", "FG3_PCT", "FTM", "FTA", "FT_PCT", "OREB", "DREB", "REB", "AST", "STL", "BLK", "TO", "PF", "PTS", "PLUS_MINUS"], "rowSet": [["0021300615", 1610612754, "IND", "Indiana", 202331, "Paul George", "F", "", "35:33", 9, 20, 0.45, 3, 7, 0.429, 2, 2, 1.0, 1, 3, 4, 2, 1, 0, 4, 1, 23, 9.0], ["0021300615", 1610612754, "IND", "Indiana", 2561, "David West", "F", "", "30:31", 6, 15, 0.4, 0, 0, 0.0, 5, 7, 0.714, 2, 3, 5, 3, 1, 2, 2, 5, 17, 2.0], ["0021300615", 1610612754, "IND", "Indiana", 201579, "Roy Hibbert", "C", "", "35:49", 7, 11, 0.636, 0, 0, 0.0, 0, 0, 0.0, 4, 9, 13, 1, 0, 2, 1, 4, 14, 9.0], ["0021300615", 1610612754, "IND", "Indiana", 202362, "Lance Stephenson", "G", "", "42:58", 6, 17, 0.353, 1, 4, 0.25, 1, 2, 0.5, 4, 6, 10, 7, 0, 0, 1, 1, 14, 2.0], ["0021300615", 1610612754, "IND", "Indiana", 201588, "George Hill", "G", "", "32:43", 5, 8, 0.625, 3, 4, 0.75, 2, 2, 1.0, 1, 3, 4, 2, 2, 0, 2, 2, 15, 4.0], ["0021300615", 1610612754, "IND", "Indiana", 201228, "CJ Watson", "", "", "15:17", 2, 4, 0.5, 1, 2, 0.5, 0, 0, 0.0, 0, 1, 1, 2, 2, 0, 1, 1, 5, 4.0], ["0021300615", 1610612754, "IND", "Indiana", 2449, "Luis Scola", "", "", "17:17", 3, 9, 0.333, 0, 0, 0.0, 0, 0, 0.0, 2, 4, 6, 1, 1, 0, 1, 1, 6, 6.0], ["0021300615", 1610612754, "IND", "Indiana", 101122, "Danny Granger", "", "", "17:49", 1, 5, 0.2, 0, 2, 0.0, 0, 0, 0.0, 0, 5, 5, 1, 0, 1, 1, 2, 2, 5.0], ["0021300615", 1610612754, "IND", "Indiana", 101133, "Ian Mahinmi", "", "", "12:04", 2, 2, 1.0, 0, 0, 0.0, 2, 2, 1.0, 3, 1, 4, 0, 0, 0, 1, 2, 6, -1.0], ["0021300615", 1610612754, "IND", "Indiana", 2446, "Rasual Butler", "", "DNP - Coach's Decision", null, null, null, null, null, null, null, null, null, null, null, null, null, null, null, null, null, null, null, null], ["0021300615", 1610612754, "IND", "Indiana", 203142, "Chris Copeland", "", "DNP - Coach's Decision", null, null, null, null, null, null, null, null, null, null, null, null, null, null, null, null, null, null, null, null], ["0021300615", 1610612754, "IND", "Indiana", 203111, "Orlando Johnson", "", "DNP - Coach's Decision", null, null, null, null, null, null, null, null, null, null, null, null, null, null, null, null, null, null, null, null], ["0021300615", 1610612754, "IND", "Indiana", 202388, "Donald Sloan", "", "DNP - Coach's Decision", null, null, null, null, null, null, null, null, null, null, null, null, null, null, null, null, null, null, null, null], ["0021300615", 1610612744, "GSW", "Golden State", 2738, "Andre Iguodala", "F", "", "29:30", 2, 5, 0.4, 1, 3, 0.333, 2, 2, 1.0, 0, 2, 2, 3, 4, 0, 3, 3, 7, -1.0], ["0021300615", 1610612744, "GSW", "Golden State", 101135, "David Lee", "F", "", "35:50", 8, 19, 0.421, 0, 0, 0.0, 4, 8, 0.5, 5, 7, 12, 2, 1, 0, 0, 5, 20, -9.0], ["0021300615", 1610612744, "GSW", "Golden State", 101106, "Andrew Bogut", "C", "", "30:53", 5, 8, 0.625, 0, 0, 0.0, 0, 0, 0.0, 3, 10, 13, 2, 1, 2, 3, 5, 10, 4.0], ["0021300615", 1610612744, "GSW", "Golden State", 202691, "Klay Thompson", "G", "", "39:26", 6, 13, 0.462, 5, 10, 0.5, 0, 0, 0.0, 0, 0, 0, 1, 0, 0, 2, 2, 17, -8.0], ["0021300615", 1610612744, "GSW", "Golden State", 201939, "Stephen Curry", "G", "", "41:28", 9, 20, 0.45, 3, 11, 0.273, 3, 4, 0.75, 0, 3, 3, 9, 0, 0, 2, 2, 24, -4.0], ["0021300615", 1610612744, "GSW", "Golden State", 203084, "Harrison Barnes", "", "", "20:56", 2, 5, 0.4, 1, 2, 0.5, 2, 2, 1.0, 1, 4, 5, 1, 1, 0, 0, 1, 7, -10.0], ["0021300615", 1610612744, "GSW", "Golden State", 201578, "Marreese Speights", "", "", "11:38", 1, 4, 0.25, 0, 0, 0.0, 0, 0, 0.0, 1, 2, 3, 0, 0, 0, 2, 1, 2, 1.0], ["0021300615", 1610612744, "GSW", "Golden State", 202348, "Jordan Crawford", "", "", "12:53", 1, 5, 0.2, 0, 2, 0.0, 0, 0, 0.0, 0, 1, 1, 3, 0, 0, 3, 1, 2, -1.0], ["0021300615", 1610612744, "GSW", "Golden State", 203110, "Draymond Green", "", "", "17:26", 1, 7, 0.143, 0, 2, 0.0, 3, 4, 0.75, 3, 3, 6, 0, 0, 0, 0, 2, 5, -12.0], ["0021300615", 1610612744, "GSW", "Golden State", 203145, "Kent Bazemore", "", "DNP - Coach's Decision", null, null, null, null, null, null, null, null, null, null, null, null, null, null, null, null, null, null, null, null], ["0021300615", 1610612744, "GSW", "Golden State", 202705, "MarShon Brooks", "", "DNP - Coach's Decision", null, null, null, null, null, null, null, null, null, null, null, null, null, null, null, null, null, null, null, null], ["0021300615", 1610612744, "GSW", "Golden State", 203517, "Nemanja Nedovic", "", "DNP - Coach's Decision", null, null, null, null, null, null, null, null, null, null, null, null, null, null, null, null, null, null, null, null]], "name": "PlayerStats"}, {"headers": ["GAME_ID", "TEAM_ID", "TEAM_NAME", "TEAM_ABBREVIATION", "TEAM_CITY", "MIN", "FGM", "FGA", "FG_PCT", "FG3M", "FG3A", "FG3_PCT", "FTM", "FTA", "FT_PCT", "OREB", "DREB", "REB", "AST", "STL", "BLK", "TO", "PF", "PTS", "PLUS_MINUS"], "rowSet": [["0021300615", 1610612754, "Pacers", "IND", "Indiana", "240:00", 41, 91, 0.451, 8, 19, 0.421, 12, 15, 0.8, 17, 35, 52, 19, 7, 5, 14, 19, 102, 8.0], ["0021300615", 1610612744, "Warriors", "GSW", "Golden State", "240:00", 35, 86, 0.407, 10, 30, 0.333, 14, 20, 0.7, 13, 32, 45, 21, 7, 2, 15, 22, 94, -8.0]], "name": "TeamStats"}, {"headers": ["LEAGUE_ID", "SEASON_ID", "TEAM_ID", "TEAM_ABBREVIATION", "TEAM_CITY", "PTS_PAINT", "PTS_2ND_CHANCE", "PTS_FB", "LARGEST_LEAD", "LEAD_CHANGES", "TIMES_TIED"], "rowSet": [["00", "22013", 1610612754, "IND", "Indiana", 46, 21, 11, 18, 3, 5], ["00", "22013", 1610612744, "GSW", "Golden State", 38, 10, 17, 20, 3, 5]], "name": "OtherStats"}, {"headers": ["OFFICIAL_ID", "FIRST_NAME", "LAST_NAME", "JERSEY_NUM"], "rowSet": [[1199, "Tom", "Washington", "49"], [1201, "Leon", "Wood", "40"], [202026, "Karl", "Lane", "77"]], "name": "Officials"}, {"headers": ["GAME_DATE", "ATTENDANCE", "GAME_TIME"], "rowSet": [["MONDAY, JANUARY 20, 2014", 19596, "2:26"]], "name": "GameInfo"}, {"headers": ["PLAYER_ID", "FIRST_NAME", "LAST_NAME", "JERSEY_NUM", "TEAM_ID", "TEAM_CITY", "TEAM_NAME", "TEAM_ABBREVIATION"], "rowSet": [[203524, "Solomon", "Hill", " 9", 1610612754, "Indiana", "Pacers", "IND"], [979, "Jermaine", "O'Neal", " 7", 1610612744, "Golden State", "Warriors", "GSW"], [203105, "Festus", "Ezeli", "31", 1610612744, "Golden State", "Warriors", "GSW"], [203136, "Ognjen", "Kuzmic", " 1", 1610612744, "Golden State", "Warriors", "GSW"]], "name": "InactivePlayers"}, {"headers": ["VIDEO_AVAILABLE_FLAG"], "rowSet": [[1]], "name": "AvailableVideo"}], "parameters": {"GameID": "0021300615", "RangeType": 0, "StartPeriod": 0, "StartRange": 0, "EndPeriod": 0, "EndRange": 0}}