{"resource": "boxscore", "resultSets": [{"headers": ["GAME_DATE_EST", "GAME_SEQUENCE", "GAME_ID", "GAME_STATUS_ID", "GAME_STATUS_TEXT", "GAMECODE", "HOME_TEAM_ID", "VISITOR_TEAM_ID", "SEASON", "LIVE_PERIOD", "LIVE_PC_TIME", "NATL_TV_BROADCASTER_ABBREVIATION", "LIVE_PERIOD_TIME_BCAST", "WH_STATUS"], "rowSet": [["2011-02-02T00:00:00", 4, "0021000722", 3, "Final", "20110202/CHADET", 1610612765, 1610612766, "2010", 4, "", null, "Q4  - ", 1]], "name": "GameSummary"}, {"headers": ["GAME_DATE_EST", "GAME_SEQUENCE", "GAME_ID", "TEAM_ID", "TEAM_ABBREVIATION", "TEAM_CITY_NAME", "TEAM_WINS_LOSSES", "PTS_QTR1", "PTS_QTR2", "PTS_QTR3", "PTS_QTR4", "PTS_OT1", "PTS_OT2", "PTS_OT3", "PTS_OT4", "PTS_OT5", "PTS_OT6", "PTS_OT7", "PTS_OT8", "PTS_OT9", "PTS_OT10", "PTS"], "rowSet": [["2011-02-02T00:00:00", 4, "0021000722", 1610612765, "DET", "Detroit", "17-32", 21, 20, 24, 22, 0, 0, 0, 0, 0, 0, 0, 0, 0, 0, 87], ["2011-02-02T00:00:00", 4, "0021000722", 1610612766, "CHA", "Charlotte", "21-27", 25, 19, 24, 29, 0, 0, 0, 0, 0, 0, 0, 0, 0, 0, 97]], "name": "LineScore"}, {"headers": ["GAME_ID", "HOME_TEAM_ID", "VISITOR_TEAM_ID", "GAME_DATE_EST", "HOME_TEAM_WINS", "HOME_TEAM_LOSSES", "SERIES_LEADER"], "rowSet": [["0021000722", 1610612765, 1610612766, "2011-02-02T00:00:00", 2, 2, "Tied"]], "name": "SeasonSeries"}, {"headers": ["GAME_ID", "LAST_GAME_ID", "LAST_GAME_DATE_EST", "LAST_GAME_HOME_TEAM_ID", "LAST_GAME_HOME_TEAM_CITY", "LAST_GAME_HOME_TEAM_NAME", "LAST_GAME_HOME_TEAM_ABBREVIATION", "LAST_GAME_HOME_TEAM_POINTS", "LAST_GAME_VISITOR_TEAM_ID", "LAST_GAME_VISITOR_TEAM_CITY", "LAST_GAME_VISITOR_TEAM_NAME", "LAST_GAME_VISITOR_TEAM_CITY1", "LAST_GAME_VISITOR_TEAM_POINTS"], "rowSet": [["0021000722", "0021000445", "2010-12-27T00:00:00", 1610612765, "Detroit", "Pistons", "DET", 100, 1610612766, "Charlotte", "Bobcats", "CHA", 105]], "name": "LastMeeting"}, {"headers": ["GAME_ID", "TEAM_ID", "TEAM_ABBREVIATION", "TEAM_CITY", "PLAYER_ID", "PLAYER_NAME", "START_POSITION", "COMMENT", "MIN", "FGM", "FGA", "FG_PCT", "FG3M", "FG3A", "FG3_PCT", "FTM", "FTA", "FT_PCT", "OREB", "DREB", "REB", "AST", "STL", "BLK", "TO", "PF", "PTS", "PLUS_MINUS"], "rowSet": [["0021000722", 1610612766, "CHA", "Charlotte", 2222, "Gerald Wallace", "F", "", "37:46", 4, 8, 0.5, 0, 1, 0.0, 2, 2, 1.0, 0, 9, 9, 3, 2, 0, 1, 1, 10, 0.0], ["0021000722", 1610612766, "CHA", "Charlotte", 2564, "Boris Diaw", "F", "", "36:01", 0, 3, 0.0, 0, 1, 0.0, 0, 0, 0.0, 0, 4, 4, 9, 1, 0, 2, 2, 0, 15.0], ["0021000722", 1610612766, "CHA", "Charlotte", 2198, "Kwame Brown", "C", "", "30:39", 6, 9, 0.667, 0, 0, 0.0, 2, 4, 0.5, 3, 7, 10, 1, 0, 1, 0, 3, 14, 4.0], ["0021000722", 1610612766, "CHA", "Charlotte", 1536, "Stephen Jackson", "G", "", "42:37", 14, 26, 0.538, 3, 7, 0.429, 8, 10, 0.8, 3, 2, 5, 4, 1, 0, 3, 4, 39, 9.0], ["0021000722", 1610612766, "CHA", "Charlotte", 201571, "D.J. Augustin", "G", "", "22:37", 2, 6, 0.333, 0, 1, 0.0, 6, 7, 0.857, 0, 3, 3, 3, 0, 0, 2, 2, 10, -2.0], ["0021000722", 1610612766, "CHA", "Charlotte", 202395, "Sherron Collins", "", "", "6:39", 2, 2, 1.0, 0, 0, 0.0, 0, 0, 0.0, 0, 2, 2, 0, 0, 0, 0, 0, 4, 9.0], ["0021000722", 1610612766, "CHA", "Charlotte", 201945, "Gerald Henderson", "", "", "23:29", 4, 9, 0.444, 0, 0, 0.0, 1, 1, 1.0, 0, 4, 4, 1, 0, 0, 1, 1, 9, 6.0], ["0021000722", 1610612766, "CHA", "Charlotte", 2733, "Shaun Livingston", "", "", "18:44", 2, 5, 0.4, 0, 0, 0.0, 1, 1, 1.0, 1, 2, 3, 5, 0, 0, 0, 3, 5, 3.0], ["0021000722", 1610612766, "CHA", "Charlotte", 1737, "Nazr Mohammed", "", "", "14:00", 3, 4, 0.75, 0, 0, 0.0, 0, 0, 0.0, 1, 2, 3, 0, 0, 0, 2, 3, 6, 5.0], ["0021000722", 1610612766, "CHA", "Charlotte", 201974, "Derrick Brown", "", "", "7:28", 0, 1, 0.0, 0, 0, 0.0, 0, 0, 0.0, 0, 3, 3, 0, 0, 0, 2, 0, 0, 1.0], ["0021000722", 1610612766, "CHA", "Charlotte", 2679, "Matt Carroll", "", "DNP - Coach's Decision", null, null, null, null, null, null, null, null, null, null, null, null, null, null, null, null, null, null, null, null], ["0021000722", 1610612766, "CHA", "Charlotte", 2059, "Eduardo Najera", "", "DNP - Coach's Decision", null, null, null, null, null, null, null, null, null, null, null, null, null, null, null, null, null, null, null, null], ["0021000722", 1610612765, "DET", "Detroit", 2419, "Tayshaun Prince", "F", "", "40:27", 8, 17, 0.471, 0, 3, 0.0, 0, 1, 0.0, 1, 2, 3, 5, 0, 1, 2, 0, 16, 5.0], ["0021000722", 1610612765, "DET", "Detroit", 2404, "Chris Wilcox", "F", "", "18:27", 3, 4, 0.75, 0, 0, 0.0, 1, 1, 1.0, 0, 5, 5, 1, 0, 0, 3, 2, 7, -1.0], ["0021000722", 1610612765, "DET", "Detroit", 202328, "Greg Monroe", "C", "", "34:57", 4, 6, 0.667, 0, 0, 0.0, 2, 3, 0.667, 1, 7, 8, 2, 1, 2, 2, 3, 10, 2.0], ["0021000722", 1610612765, "DET", "Detroit", 2732, "Ben Gordon", "G", "", "40:09", 8, 18, 0.444, 3, 7, 0.429, 1, 1, 1.0, 0, 1, 1, 4, 0, 1, 0, 4, 20, -10.0], ["0021000722", 1610612765, "DET", "Detroit", 1503, "Tracy McGrady", "G", "", "28:33", 4, 9, 0.444, 2, 2, 1.0, 2, 2, 1.0, 1, 0, 1, 8, 3, 1, 1, 4, 12, 3.0], ["0021000722", 1610612765, "DET", "Detroit", 1112, "Ben Wallace", "", "", "16:55", 0, 1, 0.0, 0, 0, 0.0, 0, 2, 0.0, 1, 3, 4, 0, 0, 2, 0, 2, 0, -16.0], ["0021000722", 1610612765, "DET", "Detroit", 101198, "Will Bynum", "", "", "19:27", 2, 9, 0.222, 0, 1, 0.0, 4, 4, 1.0, 0, 0, 0, 3, 1, 0, 1, 3, 8, -13.0], ["0021000722", 1610612765, "DET", "Detroit", 201948, "Austin Daye", "", "", "25:52", 4, 9, 0.444, 2, 4, 0.5, 1, 2, 0.5, 2, 3, 5, 0, 1, 1, 1, 2, 11, -7.0], ["0021000722", 1610612765, "DET", "Detroit", 101111, "Charlie Villanueva", "", "", "15:13", 1, 5, 0.2, 0, 2, 0.0, 1, 1, 1.0, 0, 3, 3, 0, 1, 0, 0, 1, 3, -13.0], ["0021000722", 1610612765, "DET", "Detroit", 1888, "Richard Hamilton", "", "DNP - Coach's Decision", null, null, null, null, null, null, null, null, null, null, null, null, null, null, null, null, null, null, null, null], ["0021000722", 1610612765, "DET", "Detroit", 101131, "Jason Maxiell", "", "DND - SORE BACK", null, null, null, null, null, null, null, null, null, null, null, null, null, null, null, null, null, null, null, null], ["0021000722", 1610612765, "DET", "Detroit", 201969, "DaJuan Summers", "", "DNP - Coach's Decision", null, null, null, null, null, null, null, null, null, null, null, null, null, null, null, null, null, null, null, null]], "name": "PlayerStats"}, {"headers": ["GAME_ID", "TEAM_ID", "TEAM_NAME", "TEAM_ABBREVIATION", "TEAM_CITY", "MIN", "FGM", "FGA", "FG_PCT", "FG3M", "FG3A", "FG3_PCT", "FTM", "FTA", "FT_PCT", "OREB", "DREB", "REB", "AST", "STL", "BLK", "TO", "PF", "PTS", "PLUS_MINUS"], "rowSet": [["0021000722", 1610612765, "Pistons", "DET", "Detroit", "240:00", 34, 78, 0.436, 7, 19, 0.368, 12, 17, 0.706, 6, 24, 30, 23, 7, 8, 10, 21, 87, -10.0], ["0021000722", 1610612766, "Bobcats", "CHA", "Charlotte", "240:00", 37, 73, 0.507, 3, 10, 0.3, 20, 25, 0.8, 8, 38, 46, 26, 4, 1, 13, 19, 97, 10.0]], "name": "TeamStats"}, {"headers": ["LEAGUE_ID", "SEASON_ID", "TEAM_ID", "TEAM_ABBREVIATION", "TEAM_CITY", "PTS_PAINT", "PTS_2ND_CHANCE", "PTS_FB", "LARGEST_LEAD", "LEAD_CHANGES", "TIMES_TIED"], "rowSet": [["00", "22010", 1610612765, "DET", "Detroit", 34, 5, 12, 18, 8, 3], ["00", "22010", 1610612766, "CHA", "Charlotte", 40, 7, 18, 18, 8, 3]], "name": "OtherStats"}, {"headers": ["OFFICIAL_ID", "FIRST_NAME", "LAST_NAME", "JERSEY_NUM"], "rowSet": [[1162, "Scott", "Foster", "48"], [2715, "Eric", "Lewis", "42"], [200834, "Mark", "Lindsay", "53"]], "name": "Officials"}, {"headers": ["GAME_DATE", "ATTENDANCE", "GAME_TIME"], "rowSet": [["WEDNESDAY, FEBRUARY 2, 2011", 14376, "2:13"]], "name": "GameInfo"}, {"headers": ["PLAYER_ID", "FIRST_NAME", "LAST_NAME", "JERSEY_NUM", "TEAM_ID", "TEAM_CITY", "TEAM_NAME", "TEAM_ABBREVIATION"], "rowSet": [[2205, "DeSagana", "Diop", " 7", 1610612766, "Charlotte", "Bobcats", "CHA"], [200748, "Tyrus", "Thomas", "12", 1610612766, "Charlotte", "Bobcats", "CHA"], [201187, "Dominic", "McGuire", " 5", 1610612766, "Charlotte", "Bobcats", "CHA"], [201155, "Rodney", "Stuckey", " 3", 1610612765, "Detroit", "Pistons", "DET"], [201973, "Jonas", "Jerebko", "33", 1610612765, "Detroit", "Pistons", "DET"], [202358, "Terrico", "White", "23", 1610612765, "Detroit", "Pistons", "DET"]], "name": "InactivePlayers"}, {"headers": ["VIDEO_AVAILABLE_FLAG"], "rowSet": [[0]], "name": "AvailableVideo"}], "parameters": {"GameID": "0021000722", "RangeType": 0, "StartPeriod": 0, "StartRange": 0, "EndPeriod": 0, "EndRange": 0}}