{"resource": "boxscore", "resultSets": [{"headers": ["GAME_DATE_EST", "GAME_SEQUENCE", "GAME_ID", "GAME_STATUS_ID", "GAME_STATUS_TEXT", "GAMECODE", "HOME_TEAM_ID", "VISITOR_TEAM_ID", "SEASON", "LIVE_PERIOD", "LIVE_PC_TIME", "NATL_TV_BROADCASTER_ABBREVIATION", "LIVE_PERIOD_TIME_BCAST", "WH_STATUS"], "rowSet": [["2013-02-03T00:00:00", 3, "0021200707", 3, "Final", "20130203/MIATOR", 1610612761, 1610612748, "2012", 4, "", null, "Q4  - ", 1]], "name": "GameSummary"}, {"headers": ["GAME_DATE_EST", "GAME_SEQUENCE", "GAME_ID", "TEAM_ID", "TEAM_ABBREVIATION", "TEAM_CITY_NAME", "TEAM_WINS_LOSSES", "PTS_QTR1", "PTS_QTR2", "PTS_QTR3", "PTS_QTR4", "PTS_OT1", "PTS_OT2", "PTS_OT3", "PTS_OT4", "PTS_OT5", "PTS_OT6", "PTS_OT7", "PTS_OT8", "PTS_OT9", "PTS_OT10", "PTS"], "rowSet": [["2013-02-03T00:00:00", 3, "0021200707", 1610612761, "TOR", "Toronto", "17-31", 21, 29, 17, 18, 0, 0, 0, 0, 0, 0, 0, 0, 0, 0, 85], ["2013-02-03T00:00:00", 3, "0021200707", 1610612748, "MIA", "Miami", "30-14", 24, 20, 27, 29, 0, 0, 0, 0, 0, 0, 0, 0, 0, 0, 100]], "name": "LineScore"}, {"headers": ["GAME_ID", "HOME_TEAM_ID", "VISITOR_TEAM_ID", "GAME_DATE_EST", "HOME_TEAM_WINS", "HOME_TEAM_LOSSES", "SERIES_LEADER"], "rowSet": [["0021200707", 1610612761, 1610612748, "2013-02-03T00:00:00", 0, 3, "Miami"]], "name": "SeasonSeries"}, {"headers": ["GAME_ID", "LAST_GAME_ID", "LAST_GAME_DATE_EST", "LAST_GAME_HOME_TEAM_ID", "LAST_GAME_HOME_TEAM_CITY", "LAST_GAME_HOME_TEAM_NAME", "LAST_GAME_HOME_TEAM_ABBREVIATION", "LAST_GAME_HOME_TEAM_POINTS", "LAST_GAME_VISITOR_TEAM_ID", "LAST_GAME_VISITOR_TEAM_CITY", "LAST_GAME_VISITOR_TEAM_NAME", "LAST_GAME_VISITOR_TEAM_CITY1", "LAST_GAME_VISITOR_TEAM_POINTS"], "rowSet": [["0021200707", "0021200619", "2013-01-23T00:00:00", 1610612761, "Toronto", "Raptors", "TOR", 116, 1610612748, "Miami", "Heat", "MIA", 123]], "name": "LastMeeting"}, {"headers": ["GAME_ID", "TEAM_ID", "TEAM_ABBREVIATION", "TEAM_CITY", "PLAYER_ID", "PLAYER_NAME", "START_POSITION", "COMMENT", "MIN", "FGM", "FGA", "FG_PCT", "FG3M", "FG3A", "FG3_PCT", "FTM", "FTA", "FT_PCT", "OREB", "DREB", "REB", "AST", "STL", "BLK", "TO", "PF", "PTS", "PLUS_MINUS"], "rowSet": [["0021200707", 1610612748, "MIA", "Miami", 2544, "LeBron James", "F", "", "39:44", 10, 16, 0.625, 1, 2, 0.5, 9, 11, 0.818, 0, 8, 8, 7, 2, 0, 3, 1, 30, 29.0], ["0021200707", 1610612748, "MIA", "Miami", 2617, "Udonis Haslem", "F", "", "15:38", 2, 3, 0.667, 0, 0, 0.0, 0, 0, 0.0, 2, 1, 3, 0, 0, 0, 0, 4, 4, 5.0], ["0021200707", 1610612748, "MIA", "Miami", 2547, "Chris Bosh", "C", "", "33:42", 12, 19, 0.632, 1, 1, 1.0, 3, 4, 0.75, 0, 5, 5, 0, 1, 1, 3, 3, 28, 17.0], ["0021200707", 1610612748, "MIA", "Miami", 2548, "Dwyane Wade", "G", "", "31:56", 10, 18, 0.556, 0, 1, 0.0, 3, 4, 0.75, 0, 5, 5, 5, 3, 1, 3, 3, 23, 21.0], ["0021200707", 1610612748, "MIA", "Miami", 201596, "Mario Chalmers", "G", "", "30:08", 1, 6, 0.167, 0, 2, 0.0, 0, 0, 0.0, 0, 2, 2, 5, 4, 0, 1, 3, 2, 17.0], ["0021200707", 1610612748, "MIA", "Miami", 951, "Ray Allen", "", "", "19:46", 0, 2, 0.0, 0, 2, 0.0, 1, 2, 0.5, 0, 1, 1, 2, 0, 0, 2, 1, 1, -10.0], ["0021200707", 1610612748, "MIA", "Miami", 2203, "Shane Battier", "", "", "33:43", 2, 5, 0.4, 1, 3, 0.333, 0, 0, 0.0, 2, 3, 5, 0, 0, 2, 0, 2, 5, 3.0], ["0021200707", 1610612748, "MIA", "Miami", 2365, "Chris Andersen", "", "", "11:01", 0, 1, 0.0, 0, 0, 0.0, 1, 2, 0.5, 3, 1, 4, 0, 0, 0, 0, 4, 1, 1.0], ["0021200707", 1610612748, "MIA", "Miami", 1740, "Rashard Lewis", "", "", "6:30", 1, 1, 1.0, 0, 0, 0.0, 0, 0, 0.0, 0, 1, 1, 0, 0, 0, 0, 1, 2, -6.0], ["0021200707", 1610612748, "MIA", "Miami", 202708, "Norris Cole", "", "", "17:52", 2, 4, 0.5, 0, 1, 0.0, 0, 0, 0.0, 0, 0, 0, 0, 0, 0, 0, 1, 4, -2.0], ["0021200707", 1610612748, "MIA", "Miami", 201202, "Joel Anthony", "", "DNP - Coach's Decision", null, null, null, null, null, null, null, null, null, null, null, null, null, null, null, null, null, null, null, null], ["0021200707", 1610612748, "MIA", "Miami", 2592, "James Jones", "", "DNP - Coach's Decision", null, null, null, null, null, null, null, null, null, null, null, null, null, null, null, null, null, null, null, null], ["0021200707", 1610612748, "MIA", "Miami", 2034, "Mike Miller", "", "DNP - Coach's Decision", null, null, null, null, null, null, null, null, null, null, null, null, null, null, null, null, null, null, null, null], ["0021200707", 1610612761, "TOR", "Toronto", 200752, "Rudy Gay", "F", "", "41:43", 11, 23, 0.478, 1, 5, 0.2, 6, 7, 0.857, 1, 3, 4, 2, 3, 1, 2, 4, 29, -19.0], ["0021200707", 1610612761, "TOR", "Toronto", 101161, "Amir Johnson", "F", "", "31:08", 1, 4, 0.25, 0, 0, 0.0, 0, 0, 0.0, 4, 3, 7, 2, 5, 2, 2, 4, 2, -6.0], ["0021200707", 1610612761, "TOR", "Toronto", 201189, "Aaron Gray", "C", "", "22:39", 3, 6, 0.5, 0, 0, 0.0, 0, 4, 0.0, 7, 5, 12, 0, 0, 0, 0, 2, 6, -9.0], ["0021200707", 1610612761, "TOR", "Toronto", 201942, "DeMar DeRozan", "G", "", "44:19", 6, 17, 0.353, 1, 3, 0.333, 14, 14, 1.0, 0, 3, 3, 3, 0, 0, 3, 2, 27, -21.0], ["0021200707", 1610612761, "TOR", "Toronto", 200768, "Kyle Lowry", "G", "", "30:57", 3, 7, 0.429, 1, 2, 0.5, 3, 4, 0.75, 1, 3, 4, 3, 0, 0, 5, 4, 10, -16.0], ["0021200707", 1610612761, "TOR", "Toronto", 101187, "Alan Anderson", "", "", "33:11", 1, 7, 0.143, 0, 3, 0.0, 2, 3, 0.667, 1, 2, 3, 3, 0, 0, 3, 3, 4, -1.0], ["0021200707", 1610612761, "TOR", "Toronto", 203082, "Terrence Ross", "", "", "13:43", 1, 4, 0.25, 1, 3, 0.333, 0, 0, 0.0, 0, 3, 3, 1, 0, 0, 0, 2, 3, -1.0], ["0021200707", 1610612761, "TOR", "Toronto", 101249, "John Lucas III", "", "", "17:03", 1, 6, 0.167, 0, 2, 0.0, 0, 0, 0.0, 0, 1, 1, 1, 2, 0, 0, 1, 2, 1.0], ["0021200707", 1610612761, "TOR", "Toronto", 202685, "Jonas Valanciunas", "", "", "5:17", 1, 1, 1.0, 0, 0, 0.0, 0, 0, 0.0, 0, 1, 1, 0, 0, 0, 0, 2, 2, -3.0], ["0021200707", 1610612761, "TOR", "Toronto", 203112, "Quincy Acy", "", "DNP - Coach's Decision", null, null, null, null, null, null, null, null, null, null, null, null, null, null, null, null, null, null, null, null], ["0021200707", 1610612761, "TOR", "Toronto", 202361, "Landry Fields", "", "DND - Acute Back Spasms", null, null, null, null, null, null, null, null, null, null, null, null, null, null, null, null, null, null, null, null], ["0021200707", 1610612761, "TOR", "Toronto", 101132, "Linas Kleiza", "", "DND - Sore Right Knee", null, null, null, null, null, null, null, null, null, null, null, null, null, null, null, null, null, null, null, null], ["0021200707", 1610612761, "TOR", "Toronto", 2554, "Mickael Pietrus", "", "DNP - Coach's Decision", null, null, null, null, null, null, null, null, null, null, null, null, null, null, null, null, null, null, null, null]], "name": "PlayerStats"}, {"headers": ["GAME_ID", "TEAM_ID", "TEAM_NAME", "TEAM_ABBREVIATION", "TEAM_CITY", "MIN", "FGM", "FGA", "FG_PCT", "FG3M", "FG3A", "FG3_PCT", "FTM", "FTA", "FT_PCT", "OREB", "DREB", "REB", "AST", "STL", "BLK", "TO", "PF", "PTS", "PLUS_MINUS"], "rowSet": [["0021200707", 1610612761, "Raptors", "TOR", "Toronto", "240:00", 28, 75, 0.373, 4, 18, 0.222, 25, 32, 0.781, 14, 24, 38, 15, 10, 3, 15, 24, 85, -15.0], ["0021200707", 1610612748, "Heat", "MIA", "Miami", "240:00", 40, 75, 0.533, 3, 12, 0.25, 17, 23, 0.739, 7, 27, 34, 19, 10, 4, 12, 23, 100, 15.0]], "name": "TeamStats"}, {"headers": ["LEAGUE_ID", "SEASON_ID", "TEAM_ID", "TEAM_ABBREVIATION", "TEAM_CITY", "PTS_PAINT", "PTS_2ND_CHANCE", "PTS_FB", "LARGEST_LEAD", "LEAD_CHANGES", "TIMES_TIED"], "rowSet": [["00", "22012", 1610612761, "TOR", "Toronto", 32, 16, 4, 15, 2, 5], ["00", "22012", 1610612748, "MIA", "Miami", 48, 11, 8, 15, 2, 5]], "name": "OtherStats"}, {"headers": ["OFFICIAL_ID", "FIRST_NAME", "LAST_NAME", "JERSEY_NUM"], "rowSet": [[1195, "Derrick", "Stafford", "9"], [1204, "Derek", "Richardson", "63"], [2002, "Derrick", "Collins", "11"]], "name": "Officials"}, {"headers": ["GAME_DATE", "ATTENDANCE", "GAME_TIME"], "rowSet": [["SUNDAY, FEBRUARY 3, 2013", 19800, "2:25"]], "name": "GameInfo"}, {"headers": ["PLAYER_ID", "FIRST_NAME", "LAST_NAME", "JERSEY_NUM", "TEAM_ID", "TEAM_CITY", "TEAM_NAME", "TEAM_ABBREVIATION"], "rowSet": [[202363, "Jarvis", "Varnado", "24", 1610612748, "Miami", "Heat", "MIA"], [202354, "Dexter", "Pittman", "45", 1610612748, "Miami", "Heat", "MIA"], [201632, "Hamed", "Haddadi", "99", 1610612761, "Toronto", "Raptors", "TOR"], [200745, "Andrea", "Bargnani", " 7", 1610612761, "Toronto", "Raptors", "TOR"]], "name": "InactivePlayers"}, {"headers": ["VIDEO_AVAILABLE_FLAG"], "rowSet": [[1]], "name": "AvailableVideo"}], "parameters": {"GameID": "0021200707", "RangeType": 0, "StartPeriod": 0, "StartRange": 0, "EndPeriod": 0, "EndRange": 0}}