{"resource": "boxscore", "resultSets": [{"headers": ["GAME_DATE_EST", "GAME_SEQUENCE", "GAME_ID", "GAME_STATUS_ID", "GAME_STATUS_TEXT", "GAMECODE", "HOME_TEAM_ID", "VISITOR_TEAM_ID", "SEASON", "LIVE_PERIOD", "LIVE_PC_TIME", "NATL_TV_BROADCASTER_ABBREVIATION", "LIVE_PERIOD_TIME_BCAST", "WH_STATUS"], "rowSet": [["2011-03-04T00:00:00", 6, "0021000919", 3, "Final", "20110304/CLENYK", 1610612752, 1610612739, "2010", 4, "", null, "Q4  - ", 1]], "name": "GameSummary"}, {"headers": ["GAME_DATE_EST", "GAME_SEQUENCE", "GAME_ID", "TEAM_ID", "TEAM_ABBREVIATION", "TEAM_CITY_NAME", "TEAM_WINS_LOSSES", "PTS_QTR1", "PTS_QTR2", "PTS_QTR3", "PTS_QTR4", "PTS_OT1", "PTS_OT2", "PTS_OT3", "PTS_OT4", "PTS_OT5", "PTS_OT6", "PTS_OT7", "PTS_OT8", "PTS_OT9", "PTS_OT10", "PTS"], "rowSet": [["2011-03-04T00:00:00", 6, "0021000919", 1610612739, "CLE", "Cleveland", "12-49", 32, 26, 27, 34, 0, 0, 0, 0, 0, 0, 0, 0, 0, 0, 119], ["2011-03-04T00:00:00", 6, "0021000919", 1610612752, "NYK", "New York", "31-29", 32, 32, 24, 27, 0, 0, 0, 0, 0, 0, 0, 0, 0, 0, 115]], "name": "LineScore"}, {"headers": ["GAME_ID", "HOME_TEAM_ID", "VISITOR_TEAM_ID", "GAME_DATE_EST", "HOME_TEAM_WINS", "HOME_TEAM_LOSSES", "SERIES_LEADER"], "rowSet": [["0021000919", 1610612752, 1610612739, "2011-03-04T00:00:00", 1, 3, "Cleveland"]], "name": "SeasonSeries"}, {"headers": ["GAME_ID", "LAST_GAME_ID", "LAST_GAME_DATE_EST", "LAST_GAME_HOME_TEAM_ID", "LAST_GAME_HOME_TEAM_CITY", "LAST_GAME_HOME_TEAM_NAME", "LAST_GAME_HOME_TEAM_ABBREVIATION", "LAST_GAME_HOME_TEAM_POINTS", "LAST_GAME_VISITOR_TEAM_ID", "LAST_GAME_VISITOR_TEAM_CITY", "LAST_GAME_VISITOR_TEAM_NAME", "LAST_GAME_VISITOR_TEAM_CITY1", "LAST_GAME_VISITOR_TEAM_POINTS"], "rowSet": [["0021000919", "0021000865", "2011-02-25T00:00:00", 1610612752, "New York", "Knicks", "NYK", 109, 1610612739, "Cleveland", "Cavaliers", "CLE", 115]], "name": "LastMeeting"}, {"headers": ["GAME_ID", "TEAM_ID", "TEAM_ABBREVIATION", "TEAM_CITY", "PLAYER_ID", "PLAYER_NAME", "START_POSITION", "COMMENT", "MIN", "FGM", "FGA", "FG_PCT", "FG3M", "FG3A", "FG3_PCT", "FTM", "FTA", "FT_PCT", "OREB", "DREB", "REB", "AST", "STL", "BLK", "TO", "PF", "PTS", "PLUS_MINUS"], "rowSet": [["0021000919", 1610612739, "CLE", "Cleveland", 202087, "Alonzo Gee", "F", "", "17:37", 1, 1, 1.0, 0, 0, 0.0, 2, 2, 1.0, 0, 2, 2, 0, 0, 0, 1, 4, 4, 0.0], ["0021000919", 1610612739, "CLE", "Cleveland", 202396, "Samardo Samuels", "F", "", "30:47", 5, 9, 0.556, 0, 0, 0.0, 5, 10, 0.5, 4, 2, 6, 1, 1, 0, 1, 4, 15, -3.0], ["0021000919", 1610612739, "CLE", "Cleveland", 201581, "JJ Hickson", "C", "", "35:25", 9, 17, 0.529, 0, 0, 0.0, 5, 7, 0.714, 4, 4, 8, 4, 2, 1, 3, 1, 23, 15.0], ["0021000919", 1610612739, "CLE", "Cleveland", 1515, "Anthony Parker", "G", "", "32:16", 5, 8, 0.625, 3, 5, 0.6, 0, 0, 0.0, 1, 3, 4, 7, 1, 0, 0, 1, 13, 13.0], ["0021000919", 1610612739, "CLE", "Cleveland", 201196, "Ramon Sessions", "G", "", "34:22", 4, 15, 0.267, 0, 0, 0.0, 3, 4, 0.75, 1, 1, 2, 6, 0, 0, 3, 1, 11, 2.0], ["0021000919", 1610612739, "CLE", "Cleveland", 202376, "Luke Harangody", "", "", "21:57", 6, 11, 0.545, 2, 6, 0.333, 4, 4, 1.0, 2, 2, 4, 2, 0, 0, 1, 3, 18, -1.0], ["0021000919", 1610612739, "CLE", "Cleveland", 201963, "Christian Eyenga", "", "", "24:29", 5, 7, 0.714, 3, 3, 1.0, 0, 0, 0.0, 1, 3, 4, 0, 0, 0, 1, 2, 13, -6.0], ["0021000919", 1610612739, "CLE", "Cleveland", 1884, "Baron Davis", "", "", "26:24", 6, 15, 0.4, 4, 7, 0.571, 2, 2, 1.0, 1, 2, 3, 5, 1, 0, 1, 2, 18, 10.0], ["0021000919", 1610612739, "CLE", "Cleveland", 200797, "Ryan Hollins", "", "", "7:51", 1, 2, 0.5, 0, 0, 0.0, 0, 0, 0.0, 1, 1, 2, 0, 1, 1, 1, 3, 2, -3.0], ["0021000919", 1610612739, "CLE", "Cleveland", 202412, "Manny Harris", "", "", "8:52", 1, 1, 1.0, 0, 0, 0.0, 0, 0, 0.0, 1, 1, 2, 0, 0, 0, 0, 0, 2, -7.0], ["0021000919", 1610612739, "CLE", "Cleveland", 201623, "Semih Erden", "", "DND - Strained Right Adductor", null, null, null, null, null, null, null, null, null, null, null, null, null, null, null, null, null, null, null, null], ["0021000919", 1610612739, "CLE", "Cleveland", 101121, "Joey Graham", "", "DNP - Coach's Decision", null, null, null, null, null, null, null, null, null, null, null, null, null, null, null, null, null, null, null, null], ["0021000919", 1610612752, "NYK", "New York", 2546, "Carmelo Anthony", "F", "", "42:15", 10, 16, 0.625, 1, 2, 0.5, 8, 10, 0.8, 1, 4, 5, 2, 1, 1, 6, 4, 29, -11.0], ["0021000919", 1610612752, "NYK", "New York", 2405, "Amar'e Stoudemire", "F", "", "39:28", 16, 32, 0.5, 1, 2, 0.5, 8, 10, 0.8, 4, 5, 9, 3, 0, 1, 5, 4, 41, -7.0], ["0021000919", 1610612752, "NYK", "New York", 2407, "Jared Jeffries", "C", "", "26:04", 0, 0, 0.0, 0, 0, 0.0, 1, 2, 0.5, 3, 1, 4, 2, 2, 1, 1, 6, 1, 7.0], ["0021000919", 1610612752, "NYK", "New York", 201962, "Toney Douglas", "G", "", "31:31", 5, 9, 0.556, 1, 4, 0.25, 0, 0, 0.0, 0, 5, 5, 5, 0, 0, 2, 4, 11, -4.0], ["0021000919", 1610612752, "NYK", "New York", 202361, "Landry Fields", "G", "", "34:37", 6, 8, 0.75, 3, 4, 0.75, 2, 2, 1.0, 0, 6, 6, 0, 1, 0, 1, 0, 17, 14.0], ["0021000919", 1610612752, "NYK", "New York", 200761, "Shawne Williams", "", "", "24:08", 1, 7, 0.143, 0, 3, 0.0, 0, 0, 0.0, 2, 1, 3, 1, 0, 4, 0, 3, 2, -13.0], ["0021000919", 1610612752, "NYK", "New York", 201611, "Henry Walker", "", "", "7:32", 0, 1, 0.0, 0, 1, 0.0, 0, 0, 0.0, 0, 2, 2, 0, 0, 0, 0, 0, 0, -5.0], ["0021000919", 1610612752, "NYK", "New York", 1853, "Anthony Carter", "", "", "22:04", 3, 3, 1.0, 2, 2, 1.0, 0, 0, 0.0, 0, 1, 1, 0, 0, 1, 1, 4, 8, 0.0], ["0021000919", 1610612752, "NYK", "New York", 200749, "Shelden Williams", "", "", "12:22", 1, 1, 1.0, 0, 0, 0.0, 4, 6, 0.667, 3, 1, 4, 0, 0, 1, 0, 3, 6, -1.0], ["0021000919", 1610612752, "NYK", "New York", 200764, "Renaldo Balkman", "", "DNP - Coach's Decision", null, null, null, null, null, null, null, null, null, null, null, null, null, null, null, null, null, null, null, null], ["0021000919", 1610612752, "NYK", "New York", 201974, "Derrick Brown", "", "DNP - Coach's Decision", null, null, null, null, null, null, null, null, null, null, null, null, null, null, null, null, null, null, null, null], ["0021000919", 1610612752, "NYK", "New York", 2427, "Roger Mason Jr.", "", "DNP - Coach's Decision", null, null, null, null, null, null, null, null, null, null, null, null, null, null, null, null, null, null, null, null]], "name": "PlayerStats"}, {"headers": ["GAME_ID", "TEAM_ID", "TEAM_NAME", "TEAM_ABBREVIATION", "TEAM_CITY", "MIN", "FGM", "FGA", "FG_PCT", "FG3M", "FG3A", "FG3_PCT", "FTM", "FTA", "FT_PCT", "OREB", "DREB", "REB", "AST", "STL", "BLK", "TO", "PF", "PTS", "PLUS_MINUS"], "rowSet": [["0021000919", 1610612752, "Knicks", "NYK", "New York", "240:00", 42, 77, 0.545, 8, 18, 0.444, 23, 30, 0.767, 13, 26, 39, 13, 4, 9, 16, 28, 115, -4.0], ["0021000919", 1610612739, "Cavaliers", "CLE", "Cleveland", "240:00", 43, 86, 0.5, 12, 21, 0.571, 21, 29, 0.724, 16, 21, 37, 25, 6, 2, 12, 21, 119, 4.0]], "name": "TeamStats"}, {"headers": ["LEAGUE_ID", "SEASON_ID", "TEAM_ID", "TEAM_ABBREVIATION", "TEAM_CITY", "PTS_PAINT", "PTS_2ND_CHANCE", "PTS_FB", "LARGEST_LEAD", "LEAD_CHANGES", "TIMES_TIED"], "rowSet": [["00", "22010", 1610612739, "CLE", "Cleveland", 42, 14, 4, 12, 3, 9], ["00", "22010", 1610612752, "NYK", "New York", 46, 14, 10, 12, 3, 9]], "name": "OtherStats"}, {"headers": ["OFFICIAL_ID", "FIRST_NAME", "LAST_NAME", "JERSEY_NUM"], "rowSet": [[1185, "Violet", "Palmer", "12"], [1162, "Scott", "Foster", "48"], [2002, "Derrick", "Collins", "11"]], "name": "Officials"}, {"headers": ["GAME_DATE", "ATTENDANCE", "GAME_TIME"], "rowSet": [["FRIDAY, MARCH 4, 2011", 19763, "2:25"]], "name": "GameInfo"}, {"headers": ["PLAYER_ID", "FIRST_NAME", "LAST_NAME", "JERSEY_NUM", "TEAM_ID", "TEAM_CITY", "TEAM_NAME", "TEAM_ABBREVIATION"], "rowSet": [[1712, "Antawn", "Jamison", " 4", 1610612739, "Cleveland", "Cavaliers", "CLE"], [2760, "Anderson", "Varejao", "17", 1610612739, "Cleveland", "Cavaliers", "CLE"], [200789, "Daniel", "Gibson", " 1", 1610612739, "Cleveland", "Cavaliers", "CLE"], [1497, "Chauncey", "Billups", " 4", 1610612752, "New York", "Knicks", "NYK"], [101142, "Ronny", "Turiaf", "14", 1610612752, "New York", "Knicks", "NYK"], [202360, "Andy", "Rautins", "11", 1610612752, "New York", "Knicks", "NYK"]], "name": "InactivePlayers"}, {"headers": ["VIDEO_AVAILABLE_FLAG"], "rowSet": [[0]], "name": "AvailableVideo"}], "parameters": {"GameID": "0021000919", "RangeType": 0, "StartPeriod": 0, "StartRange": 0, "EndPeriod": 0, "EndRange": 0}}