{"resource": "boxscore", "resultSets": [{"headers": ["GAME_DATE_EST", "GAME_SEQUENCE", "GAME_ID", "GAME_STATUS_ID", "GAME_STATUS_TEXT", "GAMECODE", "HOME_TEAM_ID", "VISITOR_TEAM_ID", "SEASON", "LIVE_PERIOD", "LIVE_PC_TIME", "NATL_TV_BROADCASTER_ABBREVIATION", "LIVE_PERIOD_TIME_BCAST", "WH_STATUS"], "rowSet": [["2012-01-25T00:00:00", 5, "0021100261", 3, "Final", "20120125/INDCHI", 1610612741, 1610612754, "2011", 4, "", "NBA TV", "Q4  - NBA TV", 1]], "name": "GameSummary"}, {"headers": ["GAME_DATE_EST", "GAME_SEQUENCE", "GAME_ID", "TEAM_ID", "TEAM_ABBREVIATION", "TEAM_CITY_NAME", "TEAM_WINS_LOSSES", "PTS_QTR1", "PTS_QTR2", "PTS_QTR3", "PTS_QTR4", "PTS_OT1", "PTS_OT2", "PTS_OT3", "PTS_OT4", "PTS_OT5", "PTS_OT6", "PTS_OT7", "PTS_OT8", "PTS_OT9", "PTS_OT10", "PTS"], "rowSet": [["2012-01-25T00:00:00", 5, "0021100261", 1610612754, "IND", "Indiana", "12-5", 24, 20, 31, 20, 0, 0, 0, 0, 0, 0, 0, 0, 0, 0, 95], ["2012-01-25T00:00:00", 5, "0021100261", 1610612741, "CHI", "Chicago", "16-4", 23, 31, 20, 16, 0, 0, 0, 0, 0, 0, 0, 0, 0, 0, 90]], "name": "LineScore"}, {"headers": ["GAME_ID", "HOME_TEAM_ID", "VISITOR_TEAM_ID", "GAME_DATE_EST", "HOME_TEAM_WINS", "HOME_TEAM_LOSSES", "SERIES_LEADER"], "rowSet": [["0021100261", 1610612741, 1610612754, "2012-01-25T00:00:00", 2, 1, "Chicago"]], "name": "SeasonSeries"}, {"headers": ["GAME_ID", "LAST_GAME_ID", "LAST_GAME_DATE_EST", "LAST_GAME_HOME_TEAM_ID", "LAST_GAME_HOME_TEAM_CITY", "LAST_GAME_HOME_TEAM_NAME", "LAST_GAME_HOME_TEAM_ABBREVIATION", "LAST_GAME_HOME_TEAM_POINTS", "LAST_GAME_VISITOR_TEAM_ID", "LAST_GAME_VISITOR_TEAM_CITY", "LAST_GAME_VISITOR_TEAM_NAME", "LAST_GAME_VISITOR_TEAM_CITY1", "LAST_GAME_VISITOR_TEAM_POINTS"], "rowSet": [["0021100261", "0011100017", "2011-12-20T00:00:00", 1610612741, "Chicago", "Bulls", "CHI", 93, 1610612754, "Indiana", "Pacers", "IND", 85]], "name": "LastMeeting"}, {"headers": ["GAME_ID", "TEAM_ID", "TEAM_ABBREVIATION", "TEAM_CITY", "PLAYER_ID", "PLAYER_NAME", "START_POSITION", "COMMENT", "MIN", "FGM", "FGA", "FG_PCT", "FG3M", "FG3A", "FG3_PCT", "FTM", "FTA", "FT_PCT", "OREB", "DREB", "REB", "AST", "STL", "BLK", "TO", "PF", "PTS", "PLUS_MINUS"], "rowSet": [["0021100261", 1610612754, "IND", "Indiana", 101122, "Danny Granger", "F", "", "36:50", 9, 16, 0.563, 3, 4, 0.75, 1, 2, 0.5, 3, 6, 9, 0, 2, 0, 5, 2, 22, 3.0], ["0021100261", 1610612754, "IND", "Indiana", 2561, "David West", "F", "", "33:52", 6, 18, 0.333, 0, 0, 0.0, 2, 4, 0.5, 2, 5, 7, 4, 3, 2, 0, 3, 14, 3.0], ["0021100261", 1610612754, "IND", "Indiana", 201579, "Roy Hibbert", "C", "", "34:58", 9, 14, 0.643, 0, 0, 0.0, 2, 3, 0.667, 3, 5, 8, 0, 1, 4, 1, 2, 20, 6.0], ["0021100261", 1610612754, "IND", "Indiana", 202331, "Paul George", "G", "", "33:07", 6, 12, 0.5, 1, 3, 0.333, 0, 0, 0.0, 0, 3, 3, 1, 0, 0, 1, 2, 13, 7.0], ["0021100261", 1610612754, "IND", "Indiana", 201954, "Darren Collison", "G", "", "33:01", 3, 7, 0.429, 0, 0, 0.0, 5, 6, 0.833, 2, 4, 6, 8, 0, 1, 3, 3, 11, -1.0], ["0021100261", 1610612754, "IND", "Indiana", 201588, "George Hill", "", "", "24:31", 1, 5, 0.2, 0, 2, 0.0, 0, 0, 0.0, 0, 0, 0, 2, 1, 0, 0, 3, 2, 0.0], ["0021100261", 1610612754, "IND", "Indiana", 201946, "Tyler Hansbrough", "", "", "21:35", 3, 5, 0.6, 0, 0, 0.0, 4, 6, 0.667, 0, 6, 6, 1, 1, 0, 1, 2, 10, 6.0], ["0021100261", 1610612754, "IND", "Indiana", 202362, "Lance Stephenson", "", "", "5:29", 0, 0, 0.0, 0, 0, 0.0, 0, 0, 0.0, 0, 1, 1, 2, 0, 0, 1, 0, 0, 4.0], ["0021100261", 1610612754, "IND", "Indiana", 200811, "Lou Amundson", "", "", "5:27", 0, 1, 0.0, 0, 0, 0.0, 0, 0, 0.0, 1, 0, 1, 0, 0, 0, 0, 1, 0, -5.0], ["0021100261", 1610612754, "IND", "Indiana", 2563, "Dahntay Jones", "", "", "11:10", 1, 2, 0.5, 1, 1, 1.0, 0, 0, 0.0, 0, 3, 3, 0, 0, 0, 1, 2, 3, 2.0], ["0021100261", 1610612754, "IND", "Indiana", 201965, "Jeff Ayres", "", "DNP - Coach's Decision", null, null, null, null, null, null, null, null, null, null, null, null, null, null, null, null, null, null, null, null], ["0021100261", 1610612754, "IND", "Indiana", 1902, "Jeff Foster", "", "DND - Sore Lower Back", null, null, null, null, null, null, null, null, null, null, null, null, null, null, null, null, null, null, null, null], ["0021100261", 1610612754, "IND", "Indiana", 201985, "A.J. Price", "", "NWT - Strep Throat", null, null, null, null, null, null, null, null, null, null, null, null, null, null, null, null, null, null, null, null], ["0021100261", 1610612741, "CHI", "Chicago", 200758, "Ronnie Brewer", "F", "", "41:49", 8, 15, 0.533, 0, 3, 0.0, 4, 5, 0.8, 4, 6, 10, 5, 3, 0, 2, 2, 20, 0.0], ["0021100261", 1610612741, "CHI", "Chicago", 2430, "Carlos Boozer", "F", "", "37:34", 5, 14, 0.357, 0, 0, 0.0, 1, 2, 0.5, 3, 4, 7, 3, 1, 1, 3, 5, 11, 5.0], ["0021100261", 1610612741, "CHI", "Chicago", 201149, "Joakim Noah", "C", "", "35:25", 5, 9, 0.556, 0, 0, 0.0, 0, 0, 0.0, 5, 8, 13, 3, 1, 1, 1, 4, 10, -3.0], ["0021100261", 1610612741, "CHI", "Chicago", 1888, "Richard Hamilton", "G", "", "38:13", 6, 20, 0.3, 1, 3, 0.333, 4, 5, 0.8, 0, 2, 2, 3, 0, 0, 1, 3, 17, -4.0], ["0021100261", 1610612741, "CHI", "Chicago", 201565, "Derrick Rose", "G", "", "38:00", 9, 19, 0.474, 1, 4, 0.25, 5, 5, 1.0, 1, 2, 3, 3, 1, 2, 2, 1, 24, -5.0], ["0021100261", 1610612741, "CHI", "Chicago", 202710, "Jimmy Butler", "", "", "6:11", 1, 1, 1.0, 0, 0, 0.0, 0, 0, 0.0, 0, 0, 0, 0, 0, 0, 2, 0, 2, -5.0], ["0021100261", 1610612741, "CHI", "Chicago", 2243, "Brian Scalabrine", "", "", "10:26", 1, 2, 0.5, 0, 1, 0.0, 0, 0, 0.0, 0, 1, 1, 0, 0, 1, 0, 2, 2, -10.0], ["0021100261", 1610612741, "CHI", "Chicago", 201600, "Omer Asik", "", "", "12:35", 0, 1, 0.0, 0, 0, 0.0, 0, 2, 0.0, 2, 3, 5, 1, 0, 3, 1, 1, 0, -2.0], ["0021100261", 1610612741, "CHI", "Chicago", 201228, "CJ Watson", "", "", "10:00", 0, 6, 0.0, 0, 0, 0.0, 1, 2, 0.5, 0, 0, 0, 1, 0, 0, 0, 0, 1, 0.0], ["0021100261", 1610612741, "CHI", "Chicago", 2594, "Kyle Korver", "", "", "9:47", 1, 3, 0.333, 1, 2, 0.5, 0, 0, 0.0, 0, 0, 0, 0, 0, 0, 0, 2, 3, -1.0], ["0021100261", 1610612741, "CHI", "Chicago", 2736, "Luol Deng", "", "DNP - Coach's Decision", null, null, null, null, null, null, null, null, null, null, null, null, null, null, null, null, null, null, null, null], ["0021100261", 1610612741, "CHI", "Chicago", 2229, "Mike James", "", "DNP - Coach's Decision", null, null, null, null, null, null, null, null, null, null, null, null, null, null, null, null, null, null, null, null], ["0021100261", 1610612741, "CHI", "Chicago", 101249, "John Lucas III", "", "DNP - Coach's Decision", null, null, null, null, null, null, null, null, null, null, null, null, null, null, null, null, null, null, null, null]], "name": "PlayerStats"}, {"headers": ["GAME_ID", "TEAM_ID", "TEAM_NAME", "TEAM_ABBREVIATION", "TEAM_CITY", "MIN", "FGM", "FGA", "FG_PCT", "FG3M", "FG3A", "FG3_PCT", "FTM", "FTA", "FT_PCT", "OREB", "DREB", "REB", "AST", "STL", "BLK", "TO", "PF", "PTS", "PLUS_MINUS"], "rowSet": [["0021100261", 1610612754, "Pacers", "IND", "Indiana", "240:00", 38, 80, 0.475, 5, 10, 0.5, 14, 21, 0.667, 11, 33, 44, 18, 8, 7, 13, 20, 95, 5.0], ["0021100261", 1610612741, "Bulls", "CHI", "Chicago", "240:00", 36, 90, 0.4, 3, 13, 0.231, 15, 21, 0.714, 15, 26, 41, 19, 6, 8, 12, 20, 90, -5.0]], "name": "TeamStats"}, {"headers": ["LEAGUE_ID", "SEASON_ID", "TEAM_ID", "TEAM_ABBREVIATION", "TEAM_CITY", "PTS_PAINT", "PTS_2ND_CHANCE", "PTS_FB", "LARGEST_LEAD", "LEAD_CHANGES", "TIMES_TIED"], "rowSet": [["00", "22011", 1610612741, "CHI", "Chicago", 40, 19, 20, 10, 8, 5], ["00", "22011", 1610612754, "IND", "Indiana", 50, 13, 10, 10, 8, 5]], "name": "OtherStats"}, {"headers": ["OFFICIAL_ID", "FIRST_NAME", "LAST_NAME", "JERSEY_NUM"], "rowSet": [[1830, "Marc", "Davis", "8"], [2715, "Eric", "Lewis", "42"], [101283, "Brian", "Forte", "45"]], "name": "Officials"}, {"headers": ["GAME_DATE", "ATTENDANCE", "GAME_TIME"], "rowSet": [["WEDNESDAY, JANUARY 25, 2012", 21755, "2:19"]], "name": "GameInfo"}, {"headers": ["PLAYER_ID", "FIRST_NAME", "LAST_NAME", "JERSEY_NUM", "TEAM_ID", "TEAM_CITY", "TEAM_NAME", "TEAM_ABBREVIATION"], "rowSet": [[201959, "Taj", "Gibson", "22", 1610612741, "Chicago", "Bulls", "CHI"]], "name": "InactivePlayers"}, {"headers": ["VIDEO_AVAILABLE_FLAG"], "rowSet": [[0]], "name": "AvailableVideo"}], "parameters": {"GameID": "0021100261", "RangeType": 0, "StartPeriod": 0, "StartRange": 0, "EndPeriod": 0, "EndRange": 0}}