{"resource": "boxscore", "resultSets": [{"headers": ["GAME_DATE_EST", "GAME_SEQUENCE", "GAME_ID", "GAME_STATUS_ID", "GAME_STATUS_TEXT", "GAMECODE", "HOME_TEAM_ID", "VISITOR_TEAM_ID", "SEASON", "LIVE_PERIOD", "LIVE_PC_TIME", "NATL_TV_BROADCASTER_ABBREVIATION", "LIVE_PERIOD_TIME_BCAST", "WH_STATUS"], "rowSet": [["2011-01-12T00:00:00", 9, "0021000569", 3, "Final", "20110112/NJNPHX", 1610612756, 1610612751, "2010", 5, "", null, "Q5  - ", 1]], "name": "GameSummary"}, {"headers": ["GAME_DATE_EST", "GAME_SEQUENCE", "GAME_ID", "TEAM_ID", "TEAM_ABBREVIATION", "TEAM_CITY_NAME", "TEAM_WINS_LOSSES", "PTS_QTR1", "PTS_QTR2", "PTS_QTR3", "PTS_QTR4", "PTS_OT1", "PTS_OT2", "PTS_OT3", "PTS_OT4", "PTS_OT5", "PTS_OT6", "PTS_OT7", "PTS_OT8", "PTS_OT9", "PTS_OT10", "PTS"], "rowSet": [["2011-01-12T00:00:00", 9, "0021000569", 1610612751, "NJN", "New Jersey", "10-28", 28, 29, 27, 19, 6, 0, 0, 0, 0, 0, 0, 0, 0, 0, 109], ["2011-01-12T00:00:00", 9, "0021000569", 1610612756, "PHX", "Phoenix", "16-21", 28, 27, 18, 30, 15, 0, 0, 0, 0, 0, 0, 0, 0, 0, 118]], "name": "LineScore"}, {"headers": ["GAME_ID", "HOME_TEAM_ID", "VISITOR_TEAM_ID", "GAME_DATE_EST", "HOME_TEAM_WINS", "HOME_TEAM_LOSSES", "SERIES_LEADER"], "rowSet": [["0021000569", 1610612756, 1610612751, "2011-01-12T00:00:00", 2, 0, "Phoenix"]], "name": "SeasonSeries"}, {"headers": ["GAME_ID", "LAST_GAME_ID", "LAST_GAME_DATE_EST", "LAST_GAME_HOME_TEAM_ID", "LAST_GAME_HOME_TEAM_CITY", "LAST_GAME_HOME_TEAM_NAME", "LAST_GAME_HOME_TEAM_ABBREVIATION", "LAST_GAME_HOME_TEAM_POINTS", "LAST_GAME_VISITOR_TEAM_ID", "LAST_GAME_VISITOR_TEAM_CITY", "LAST_GAME_VISITOR_TEAM_NAME", "LAST_GAME_VISITOR_TEAM_CITY1", "LAST_GAME_VISITOR_TEAM_POINTS"], "rowSet": [["0021000569", "0020901113", "2010-03-31T00:00:00", 1610612756, "Phoenix", "Suns", "PHX", 116, 1610612751, "New Jersey", "Nets", "NJN", 105]], "name": "LastMeeting"}, {"headers": ["GAME_ID", "TEAM_ID", "TEAM_ABBREVIATION", "TEAM_CITY", "PLAYER_ID", "PLAYER_NAME", "START_POSITION", "COMMENT", "MIN", "FGM", "FGA", "FG_PCT", "FG3M", "FG3A", "FG3_PCT", "FTM", "FTA", "FT_PCT", "OREB", "DREB", "REB", "AST", "STL", "BLK", "TO", "PF", "PTS", "PLUS_MINUS"], "rowSet": [["0021000569", 1610612751, "NJN", "New Jersey", 2566, "Travis Outlaw", "F", "", "37:47", 2, 12, 0.167, 0, 6, 0.0, 1, 2, 0.5, 1, 10, 11, 3, 2, 0, 0, 3, 5, -2.0], ["0021000569", 1610612751, "NJN", "New Jersey", 202324, "Derrick Favors", "F", "", "18:24", 5, 8, 0.625, 0, 0, 0.0, 2, 3, 0.667, 2, 0, 2, 0, 1, 0, 0, 2, 12, 1.0], ["0021000569", 1610612751, "NJN", "New Jersey", 201572, "Brook Lopez", "C", "", "29:43", 7, 13, 0.538, 0, 0, 0.0, 2, 2, 1.0, 1, 7, 8, 0, 0, 0, 4, 3, 16, 0.0], ["0021000569", 1610612751, "NJN", "New Jersey", 101211, "Stephen Graham", "G", "", "14:12", 1, 2, 0.5, 0, 0, 0.0, 0, 0, 0.0, 0, 4, 4, 1, 0, 0, 2, 4, 2, 5.0], ["0021000569", 1610612751, "NJN", "New Jersey", 2734, "Devin Harris", "G", "", "38:40", 5, 12, 0.417, 1, 4, 0.25, 4, 6, 0.667, 0, 1, 1, 15, 3, 0, 5, 6, 15, -16.0], ["0021000569", 1610612751, "NJN", "New Jersey", 2624, "Quinton Ross", "", "", "16:33", 3, 5, 0.6, 0, 1, 0.0, 0, 0, 0.0, 0, 0, 0, 1, 0, 0, 0, 3, 6, -5.0], ["0021000569", 1610612751, "NJN", "New Jersey", 2743, "Kris Humphries", "", "", "32:55", 6, 11, 0.545, 0, 0, 0.0, 4, 5, 0.8, 1, 5, 6, 2, 0, 3, 0, 5, 16, -7.0], ["0021000569", 1610612751, "NJN", "New Jersey", 2756, "Sasha Vujacic", "", "", "37:02", 7, 13, 0.538, 5, 8, 0.625, 0, 0, 0.0, 0, 3, 3, 4, 3, 0, 1, 4, 19, -16.0], ["0021000569", 1610612751, "NJN", "New Jersey", 101130, "Johan Petro", "", "", "13:53", 2, 4, 0.5, 0, 0, 0.0, 2, 2, 1.0, 2, 0, 2, 0, 1, 0, 0, 2, 6, -1.0], ["0021000569", 1610612751, "NJN", "New Jersey", 200770, "Jordan Farmar", "", "", "25:51", 4, 8, 0.5, 2, 6, 0.333, 2, 2, 1.0, 0, 2, 2, 6, 1, 0, 2, 4, 12, -4.0], ["0021000569", 1610612751, "NJN", "New Jersey", 201627, "Anthony Morrow", "", "DND - Strained Right Hamstring", null, null, null, null, null, null, null, null, null, null, null, null, null, null, null, null, null, null, null, null], ["0021000569", 1610612751, "NJN", "New Jersey", 202386, "Ben Uzoh", "", "DNP - Coach's Decision", null, null, null, null, null, null, null, null, null, null, null, null, null, null, null, null, null, null, null, null], ["0021000569", 1610612756, "PHX", "Phoenix", 2735, "Josh Childress", "F", "", "21:07", 1, 4, 0.25, 0, 3, 0.0, 0, 0, 0.0, 2, 2, 4, 1, 0, 0, 2, 1, 2, -12.0], ["0021000569", 1610612756, "PHX", "Phoenix", 101112, "Channing Frye", "F", "", "44:11", 7, 13, 0.538, 2, 3, 0.667, 5, 6, 0.833, 1, 6, 7, 0, 1, 1, 3, 5, 21, 12.0], ["0021000569", 1610612756, "PHX", "Phoenix", 201577, "Robin Lopez", "C", "", "20:54", 5, 8, 0.625, 0, 0, 0.0, 1, 1, 1.0, 0, 2, 2, 0, 0, 0, 2, 3, 11, -14.0], ["0021000569", 1610612756, "PHX", "Phoenix", 1713, "Vince Carter", "G", "", "41:11", 9, 20, 0.45, 4, 9, 0.444, 1, 2, 0.5, 2, 3, 5, 2, 0, 0, 2, 2, 23, 16.0], ["0021000569", 1610612756, "PHX", "Phoenix", 959, "Steve Nash", "G", "", "41:50", 6, 17, 0.353, 0, 0, 0.0, 11, 11, 1.0, 1, 6, 7, 16, 1, 0, 3, 3, 23, 13.0], ["0021000569", 1610612756, "PHX", "Phoenix", 101124, "Hakim Warrick", "", "", "13:18", 1, 2, 0.5, 0, 0, 0.0, 4, 4, 1.0, 0, 4, 4, 1, 1, 0, 1, 2, 6, 7.0], ["0021000569", 1610612756, "PHX", "Phoenix", 201162, "Jared Dudley", "", "", "32:54", 4, 7, 0.571, 1, 3, 0.333, 6, 9, 0.667, 2, 3, 5, 1, 1, 0, 2, 3, 15, 14.0], ["0021000569", 1610612756, "PHX", "Phoenix", 101162, "Marcin Gortat", "", "", "20:07", 3, 6, 0.5, 0, 0, 0.0, 2, 2, 1.0, 1, 5, 6, 0, 0, 2, 0, 1, 8, -5.0], ["0021000569", 1610612756, "PHX", "Phoenix", 201609, "Goran Dragic", "", "", "29:28", 2, 5, 0.4, 0, 1, 0.0, 5, 7, 0.714, 1, 4, 5, 4, 0, 0, 1, 1, 9, 14.0], ["0021000569", 1610612756, "PHX", "Phoenix", 202220, "Zabian Dowdell", "", "DNP - Coach's Decision", null, null, null, null, null, null, null, null, null, null, null, null, null, null, null, null, null, null, null, null], ["0021000569", 1610612756, "PHX", "Phoenix", 2554, "Mickael Pietrus", "", "DNP - Coach's Decision", null, null, null, null, null, null, null, null, null, null, null, null, null, null, null, null, null, null, null, null], ["0021000569", 1610612756, "PHX", "Phoenix", 202081, "Garret Siler", "", "DNP - Coach's Decision", null, null, null, null, null, null, null, null, null, null, null, null, null, null, null, null, null, null, null, null]], "name": "PlayerStats"}, {"headers": ["GAME_ID", "TEAM_ID", "TEAM_NAME", "TEAM_ABBREVIATION", "TEAM_CITY", "MIN", "FGM", "FGA", "FG_PCT", "FG3M", "FG3A", "FG3_PCT", "FTM", "FTA", "FT_PCT", "OREB", "DREB", "REB", "AST", "STL", "BLK", "TO", "PF", "PTS", "PLUS_MINUS"], "rowSet": [["0021000569", 1610612756, "Suns", "PHX", "Phoenix", "265:00", 38, 82, 0.463, 7, 19, 0.368, 35, 42, 0.833, 10, 35, 45, 25, 4, 3, 16, 21, 118, 9.0], ["0021000569", 1610612751, "Nets", "NJN", "New Jersey", "265:00", 42, 88, 0.477, 8, 25, 0.32, 17, 22, 0.773, 7, 32, 39, 32, 11, 3, 14, 36, 109, -9.0]], "name": "TeamStats"}, {"headers": ["LEAGUE_ID", "SEASON_ID", "TEAM_ID", "TEAM_ABBREVIATION", "TEAM_CITY", "PTS_PAINT", "PTS_2ND_CHANCE", "PTS_FB", "LARGEST_LEAD", "LEAD_CHANGES", "TIMES_TIED"], "rowSet": [["00", "22010", 1610612756, "PHX", "Phoenix", 50, 13, 15, 15, 19, 15], ["00", "22010", 1610612751, "NJN", "New Jersey", 38, 11, 12, 15, 19, 15]], "name": "OtherStats"}, {"headers": ["OFFICIAL_ID", "FIRST_NAME", "LAST_NAME", "JERSEY_NUM"], "rowSet": [[1148, "James", "Capers", "19"], [2882, "Sean", "Wright", "65"], [2716, "Olandis", "Poole", "50"]], "name": "Officials"}, {"headers": ["GAME_DATE", "ATTENDANCE", "GAME_TIME"], "rowSet": [["WEDNESDAY, JANUARY 12, 2011", 16334, "2:50"]], "name": "GameInfo"}, {"headers": ["PLAYER_ID", "FIRST_NAME", "LAST_NAME", "JERSEY_NUM", "TEAM_ID", "TEAM_CITY", "TEAM_NAME", "TEAM_ABBREVIATION"], "rowSet": [[2211, "Troy", "Murphy", " 7", 1610612751, "New Jersey", "Nets", "NJN"], [202345, "Damion", "James", "10", 1610612751, "New Jersey", "Nets", "NJN"], [255, "Grant", "Hill", "33", 1610612756, "Phoenix", "Suns", "PHX"], [202371, "Gani", "Lawal", "31", 1610612756, "Phoenix", "Suns", "PHX"]], "name": "InactivePlayers"}, {"headers": ["VIDEO_AVAILABLE_FLAG"], "rowSet": [[0]], "name": "AvailableVideo"}], "parameters": {"GameID": "0021000569", "RangeType": 0, "StartPeriod": 0, "StartRange": 0, "EndPeriod": 0, "EndRange": 0}}