{"resource": "boxscore", "resultSets": [{"headers": ["GAME_DATE_EST", "GAME_SEQUENCE", "GAME_ID", "GAME_STATUS_ID", "GAME_STATUS_TEXT", "GAMECODE", "HOME_TEAM_ID", "VISITOR_TEAM_ID", "SEASON", "LIVE_PERIOD", "LIVE_PC_TIME", "NATL_TV_BROADCASTER_ABBREVIATION", "LIVE_PERIOD_TIME_BCAST", "WH_STATUS"], "rowSet": [["2013-03-30T00:00:00", 6, "0021201090", 3, "Final", "20130330/OKCMIL", 1610612749, 1610612760, "2012", 4, "", null, "Q4  - ", 1]], "name": "GameSummary"}, {"headers": ["GAME_DATE_EST", "GAME_SEQUENCE", "GAME_ID", "TEAM_ID", "TEAM_ABBREVIATION", "TEAM_CITY_NAME", "TEAM_WINS_LOSSES", "PTS_QTR1", "PTS_QTR2", "PTS_QTR3", "PTS_QTR4", "PTS_OT1", "PTS_OT2", "PTS_OT3", "PTS_OT4", "PTS_OT5", "PTS_OT6", "PTS_OT7", "PTS_OT8", "PTS_OT9", "PTS_OT10", "PTS"], "rowSet": [["2013-03-30T00:00:00", 6, "0021201090", 1610612749, "MIL", "Milwaukee", "35-37", 28, 18, 37, 16, 0, 0, 0, 0, 0, 0, 0, 0, 0, 0, 99], ["2013-03-30T00:00:00", 6, "0021201090", 1610612760, "OKC", "Oklahoma City", "54-20", 32, 24, 27, 26, 0, 0, 0, 0, 0, 0, 0, 0, 0, 0, 109]], "name": "LineScore"}, {"headers": ["GAME_ID", "HOME_TEAM_ID", "VISITOR_TEAM_ID", "GAME_DATE_EST", "HOME_TEAM_WINS", "HOME_TEAM_LOSSES", "SERIES_LEADER"], "rowSet": [["0021201090", 1610612749, 1610612760, "2013-03-30T00:00:00", 1, 1, "Tied"]], "name": "SeasonSeries"}, {"headers": ["GAME_ID", "LAST_GAME_ID", "LAST_GAME_DATE_EST", "LAST_GAME_HOME_TEAM_ID", "LAST_GAME_HOME_TEAM_CITY", "LAST_GAME_HOME_TEAM_NAME", "LAST_GAME_HOME_TEAM_ABBREVIATION", "LAST_GAME_HOME_TEAM_POINTS", "LAST_GAME_VISITOR_TEAM_ID", "LAST_GAME_VISITOR_TEAM_CITY", "LAST_GAME_VISITOR_TEAM_NAME", "LAST_GAME_VISITOR_TEAM_CITY1", "LAST_GAME_VISITOR_TEAM_POINTS"], "rowSet": [["0021201090", "0021100845", "2012-04-09T00:00:00", 1610612749, "Milwaukee", "Bucks", "MIL", 89, 1610612760, "Oklahoma City", "Thunder", "OKC", 109]], "name": "LastMeeting"}, {"headers": ["GAME_ID", "TEAM_ID", "TEAM_ABBREVIATION", "TEAM_CITY", "PLAYER_ID", "PLAYER_NAME", "START_POSITION", "COMMENT", "MIN", "FGM", "FGA", "FG_PCT", "FG3M", "FG3A", "FG3_PCT", "FTM", "FTA", "FT_PCT", "OREB", "DREB", "REB", "AST", "STL", "BLK", "TO", "PF", "PTS", "PLUS_MINUS"], "rowSet": [["0021201090", 1610612760, "OKC", "Oklahoma City", 201142, "Kevin Durant", "F", "", "37:50", 10, 19, 0.526, 1, 2, 0.5, 9, 10, 0.9, 1, 7, 8, 5, 0, 1, 2, 0, 30, 19.0], ["0021201090", 1610612760, "OKC", "Oklahoma City", 201586, "Serge Ibaka", "F", "", "30:57", 7, 8, 0.875, 0, 1, 0.0, 2, 3, 0.667, 3, 4, 7, 0, 0, 8, 1, 1, 16, 9.0], ["0021201090", 1610612760, "OKC", "Oklahoma City", 2570, "Kendrick Perkins", "C", "", "18:05", 2, 4, 0.5, 0, 0, 0.0, 0, 0, 0.0, 0, 4, 4, 0, 0, 0, 0, 4, 4, 4.0], ["0021201090", 1610612760, "OKC", "Oklahoma City", 200757, "Thabo Sefolosha", "G", "", "17:12", 1, 3, 0.333, 1, 2, 0.5, 0, 0, 0.0, 0, 1, 1, 3, 0, 0, 1, 1, 3, 4.0], ["0021201090", 1610612760, "OKC", "Oklahoma City", 201566, "Russell Westbrook", "G", "", "37:13", 6, 18, 0.333, 1, 4, 0.25, 10, 14, 0.714, 2, 11, 13, 10, 3, 1, 5, 4, 23, 7.0], ["0021201090", 1610612760, "OKC", "Oklahoma City", 2755, "Kevin Martin", "", "", "30:48", 6, 12, 0.5, 1, 6, 0.167, 4, 5, 0.8, 1, 4, 5, 2, 1, 0, 1, 3, 17, 6.0], ["0021201090", 1610612760, "OKC", "Oklahoma City", 2555, "Nick Collison", "", "", "24:08", 5, 6, 0.833, 0, 0, 0.0, 0, 0, 0.0, 3, 3, 6, 2, 1, 1, 1, 2, 10, -7.0], ["0021201090", 1610612760, "OKC", "Oklahoma City", 200758, "Ronnie Brewer", "", "", "6:43", 0, 0, 0.0, 0, 0, 0.0, 0, 0, 0.0, 0, 2, 2, 1, 0, 0, 0, 0, 0, -3.0], ["0021201090", 1610612760, "OKC", "Oklahoma City", 965, "Derek Fisher", "", "", "22:27", 1, 2, 0.5, 0, 1, 0.0, 0, 0, 0.0, 0, 2, 2, 0, 1, 1, 1, 4, 2, 12.0], ["0021201090", 1610612760, "OKC", "Oklahoma City", 202704, "Reggie Jackson", "", "", "14:37", 2, 3, 0.667, 0, 0, 0.0, 0, 0, 0.0, 0, 0, 0, 1, 1, 0, 1, 1, 4, -1.0], ["0021201090", 1610612760, "OKC", "Oklahoma City", 203103, "Perry Jones", "", "DNP - Coach's Decision", null, null, null, null, null, null, null, null, null, null, null, null, null, null, null, null, null, null, null, null], ["0021201090", 1610612760, "OKC", "Oklahoma City", 203087, "Jeremy Lamb", "", "DNP - Coach's Decision", null, null, null, null, null, null, null, null, null, null, null, null, null, null, null, null, null, null, null, null], ["0021201090", 1610612760, "OKC", "Oklahoma City", 201934, "Hasheem Thabeet", "", "DNP - Coach's Decision", null, null, null, null, null, null, null, null, null, null, null, null, null, null, null, null, null, null, null, null], ["0021201090", 1610612749, "MIL", "Milwaukee", 2605, "Marquis Daniels", "F", "", "32:19", 4, 12, 0.333, 1, 3, 0.333, 3, 4, 0.75, 3, 0, 3, 3, 3, 0, 3, 3, 12, -4.0], ["0021201090", 1610612749, "MIL", "Milwaukee", 101141, "Ersan Ilyasova", "F", "", "33:56", 12, 22, 0.545, 4, 6, 0.667, 1, 1, 1.0, 4, 10, 14, 2, 1, 0, 1, 3, 29, 4.0], ["0021201090", 1610612749, "MIL", "Milwaukee", 202336, "Larry Sanders", "C", "", "29:51", 5, 9, 0.556, 0, 0, 0.0, 2, 2, 1.0, 4, 6, 10, 1, 0, 0, 0, 3, 12, -9.0], ["0021201090", 1610612749, "MIL", "Milwaukee", 101145, "Monta Ellis", "G", "", "39:10", 3, 17, 0.176, 2, 5, 0.4, 1, 2, 0.5, 1, 1, 2, 7, 2, 0, 2, 3, 9, -2.0], ["0021201090", 1610612749, "MIL", "Milwaukee", 201943, "Brandon Jennings", "G", "", "37:36", 3, 13, 0.231, 2, 8, 0.25, 0, 0, 0.0, 0, 1, 1, 4, 0, 0, 2, 2, 8, -21.0], ["0021201090", 1610612749, "MIL", "Milwaukee", 201601, "Luc Mbah a Moute", "", "", "18:33", 2, 5, 0.4, 1, 2, 0.5, 0, 0, 0.0, 0, 1, 1, 2, 1, 0, 0, 3, 5, -12.0], ["0021201090", 1610612749, "MIL", "Milwaukee", 202327, "Ekpe Udoh", "", "", "18:09", 4, 6, 0.667, 0, 0, 0.0, 6, 6, 1.0, 5, 6, 11, 1, 0, 2, 0, 3, 14, -1.0], ["0021201090", 1610612749, "MIL", "Milwaukee", 200755, "JJ Redick", "", "", "23:51", 4, 12, 0.333, 2, 5, 0.4, 0, 0, 0.0, 2, 0, 2, 4, 0, 0, 1, 0, 10, -4.0], ["0021201090", 1610612749, "MIL", "Milwaukee", 2399, "Mike Dunleavy", "", "", "6:35", 0, 2, 0.0, 0, 0, 0.0, 0, 0, 0.0, 0, 1, 1, 0, 0, 0, 0, 0, 0, -1.0], ["0021201090", 1610612749, "MIL", "Milwaukee", 2223, "Samuel Dalembert", "", "DNP - Coach's Decision", null, null, null, null, null, null, null, null, null, null, null, null, null, null, null, null, null, null, null, null], ["0021201090", 1610612749, "MIL", "Milwaukee", 2400, "Drew Gooden", "", "DNP - Coach's Decision", null, null, null, null, null, null, null, null, null, null, null, null, null, null, null, null, null, null, null, null], ["0021201090", 1610612749, "MIL", "Milwaukee", 203089, "John Henson", "", "DNP - Coach's Decision", null, null, null, null, null, null, null, null, null, null, null, null, null, null, null, null, null, null, null, null], ["0021201090", 1610612749, "MIL", "Milwaukee", 202397, "Ish Smith", "", "DNP - Coach's Decision", null, null, null, null, null, null, null, null, null, null, null, null, null, null, null, null, null, null, null, null]], "name": "PlayerStats"}, {"headers": ["GAME_ID", "TEAM_ID", "TEAM_NAME", "TEAM_ABBREVIATION", "TEAM_CITY", "MIN", "FGM", "FGA", "FG_PCT", "FG3M", "FG3A", "FG3_PCT", "FTM", "FTA", "FT_PCT", "OREB", "DREB", "REB", "AST", "STL", "BLK", "TO", "PF", "PTS", "PLUS_MINUS"], "rowSet": [["0021201090", 1610612760, "Thunder", "OKC", "Oklahoma City", "240:00", 40, 75, 0.533, 4, 16, 0.25, 25, 32, 0.781, 10, 38, 48, 24, 7, 12, 13, 20, 109, 10.0], ["0021201090", 1610612749, "Bucks", "MIL", "Milwaukee", "240:00", 37, 98, 0.378, 12, 29, 0.414, 13, 15, 0.867, 19, 26, 45, 24, 7, 2, 9, 20, 99, -10.0]], "name": "TeamStats"}, {"headers": ["LEAGUE_ID", "SEASON_ID", "TEAM_ID", "TEAM_ABBREVIATION", "TEAM_CITY", "PTS_PAINT", "PTS_2ND_CHANCE", "PTS_FB", "LARGEST_LEAD", "LEAD_CHANGES", "TIMES_TIED"], "rowSet": [["00", "22012", 1610612760, "OKC", "Oklahoma City", 48, 13, 15, 11, 11, 10], ["00", "22012", 1610612749, "MIL", "Milwaukee", 38, 20, 4, 12, 11, 10]], "name": "OtherStats"}, {"headers": ["OFFICIAL_ID", "FIRST_NAME", "LAST_NAME", "JERSEY_NUM"], "rowSet": [[1168, "David", "Jones", "36"], [101283, "Brian", "Forte", "45"], [200832, "Curtis", "Blair", "74"]], "name": "Officials"}, {"headers": ["GAME_DATE", "ATTENDANCE", "GAME_TIME"], "rowSet": [["SATURDAY, MARCH 30, 2013", 17578, "2:11"]], "name": "GameInfo"}, {"headers": ["PLAYER_ID", "FIRST_NAME", "LAST_NAME", "JERSEY_NUM", "TEAM_ID", "TEAM_CITY", "TEAM_NAME", "TEAM_ABBREVIATION"], "rowSet": [[202970, "Gustavo", "Ayon", "19", 1610612749, "Milwaukee", "Bucks", "MIL"], [2038, "Joel", "Przybilla", "10", 1610612749, "Milwaukee", "Bucks", "MIL"], [202732, "DeAndre", "Liggins", "25", 1610612760, "Oklahoma City", "Thunder", "OKC"], [202350, "Daniel", "Orton", "33", 1610612760, "Oklahoma City", "Thunder", "OKC"]], "name": "InactivePlayers"}, {"headers": ["VIDEO_AVAILABLE_FLAG"], "rowSet": [[1]], "name": "AvailableVideo"}], "parameters": {"GameID": "0021201090", "RangeType": 0, "StartPeriod": 0, "StartRange": 0, "EndPeriod": 0, "EndRange": 0}}